{
"meta":{"test_sets":[],"test_metrics":[],"learn_metrics":[{"best_value":"Min","name":"RMSE"}],"launch_mode":"Train","parameters":"","iteration_count":1000,"learn_sets":["learn"],"name":"experiment"},
"iterations":[
{"learn":[14.59871775],"iteration":0,"passed_time":0.1405732802,"remaining_time":140.4327069},
{"learn":[14.22518863],"iteration":1,"passed_time":0.1426510502,"remaining_time":71.18287407},
{"learn":[13.8866124],"iteration":2,"passed_time":0.144801379,"remaining_time":48.12232497},
{"learn":[13.52356875],"iteration":3,"passed_time":0.1468889331,"remaining_time":36.57534433},
{"learn":[13.18870211],"iteration":4,"passed_time":0.1489635562,"remaining_time":29.64374769},
{"learn":[12.9124226],"iteration":5,"passed_time":0.1506897414,"remaining_time":24.96426716},
{"learn":[12.60003351],"iteration":6,"passed_time":0.15250146,"remaining_time":21.63342139},
{"learn":[12.32990573],"iteration":7,"passed_time":0.1542400218,"remaining_time":19.12576271},
{"learn":[12.0660619],"iteration":8,"passed_time":0.1570207955,"remaining_time":17.28973426},
{"learn":[11.77309809],"iteration":9,"passed_time":0.160183777,"remaining_time":15.85819392},
{"learn":[11.49227636],"iteration":10,"passed_time":0.1623374001,"remaining_time":14.59560806},
{"learn":[11.26264833],"iteration":11,"passed_time":0.1645600032,"remaining_time":13.5487736},
{"learn":[11.04260393],"iteration":12,"passed_time":0.1674337425,"remaining_time":12.71208491},
{"learn":[10.79916926],"iteration":13,"passed_time":0.1703395087,"remaining_time":11.99676826},
{"learn":[10.5541002],"iteration":14,"passed_time":0.1734076789,"remaining_time":11.38710425},
{"learn":[10.31918115],"iteration":15,"passed_time":0.1759494168,"remaining_time":10.82088914},
{"learn":[10.10004441],"iteration":16,"passed_time":0.1788224088,"remaining_time":10.34014281},
{"learn":[9.894556723],"iteration":17,"passed_time":0.182048225,"remaining_time":9.931742051},
{"learn":[9.690174082],"iteration":18,"passed_time":0.1857947087,"remaining_time":9.592874172},
{"learn":[9.506034866],"iteration":19,"passed_time":0.1891060333,"remaining_time":9.266195631},
{"learn":[9.338524633],"iteration":20,"passed_time":0.1920732325,"remaining_time":8.954271172},
{"learn":[9.170203312],"iteration":21,"passed_time":0.1938141848,"remaining_time":8.615921487},
{"learn":[9.010299969],"iteration":22,"passed_time":0.19574579,"remaining_time":8.314940732},
{"learn":[8.843866678],"iteration":23,"passed_time":0.1982826623,"remaining_time":8.063494934},
{"learn":[8.690548059],"iteration":24,"passed_time":0.2009113956,"remaining_time":7.835544428},
{"learn":[8.555307687],"iteration":25,"passed_time":0.2021935181,"remaining_time":7.574480257},
{"learn":[8.413851302],"iteration":26,"passed_time":0.2028930301,"remaining_time":7.31166364},
{"learn":[8.29256019],"iteration":27,"passed_time":0.2041886585,"remaining_time":7.088263431},
{"learn":[8.162193833],"iteration":28,"passed_time":0.2056351869,"remaining_time":6.885233328},
{"learn":[8.040736294],"iteration":29,"passed_time":0.2074461701,"remaining_time":6.707426166},
{"learn":[7.921220278],"iteration":30,"passed_time":0.2094627905,"remaining_time":6.547401419},
{"learn":[7.809589039],"iteration":31,"passed_time":0.2114218073,"remaining_time":6.395509671},
{"learn":[7.699675801],"iteration":32,"passed_time":0.2127931152,"remaining_time":6.235483104},
{"learn":[7.60645267],"iteration":33,"passed_time":0.2146143149,"remaining_time":6.097571417},
{"learn":[7.498880302],"iteration":34,"passed_time":0.2163066112,"remaining_time":5.963882279},
{"learn":[7.401158744],"iteration":35,"passed_time":0.2179881037,"remaining_time":5.837237},
{"learn":[7.306431077],"iteration":36,"passed_time":0.2191728567,"remaining_time":5.704417866},
{"learn":[7.223863468],"iteration":37,"passed_time":0.2205631702,"remaining_time":5.583730784},
{"learn":[7.143477682],"iteration":38,"passed_time":0.2220248158,"remaining_time":5.470919179},
{"learn":[7.062817131],"iteration":39,"passed_time":0.2238276658,"remaining_time":5.371863979},
{"learn":[6.990793435],"iteration":40,"passed_time":0.2254183133,"remaining_time":5.272589329},
{"learn":[6.931862224],"iteration":41,"passed_time":0.2262673701,"remaining_time":5.161050965},
{"learn":[6.858296558],"iteration":42,"passed_time":0.2269940472,"remaining_time":5.051937283},
{"learn":[6.786268161],"iteration":43,"passed_time":0.2281961496,"remaining_time":4.958079978},
{"learn":[6.717118549],"iteration":44,"passed_time":0.2294415998,"remaining_time":4.869260618},
{"learn":[6.652948106],"iteration":45,"passed_time":0.2307367714,"remaining_time":4.785279999},
{"learn":[6.589686076],"iteration":46,"passed_time":0.2321177259,"remaining_time":4.706557294},
{"learn":[6.531283097],"iteration":47,"passed_time":0.2334954218,"remaining_time":4.630992531},
{"learn":[6.471368031],"iteration":48,"passed_time":0.2348671576,"remaining_time":4.558340141},
{"learn":[6.416481395],"iteration":49,"passed_time":0.2369053495,"remaining_time":4.50120164},
{"learn":[6.369870822],"iteration":50,"passed_time":0.2384290113,"remaining_time":4.436649642},
{"learn":[6.325678067],"iteration":51,"passed_time":0.2403569688,"remaining_time":4.38189243},
{"learn":[6.275766122],"iteration":52,"passed_time":0.2421628809,"remaining_time":4.326948079},
{"learn":[6.224773967],"iteration":53,"passed_time":0.2437021569,"remaining_time":4.269300749},
{"learn":[6.182249254],"iteration":54,"passed_time":0.2450583282,"remaining_time":4.210547639},
{"learn":[6.139904173],"iteration":55,"passed_time":0.2462309103,"remaining_time":4.150749631},
{"learn":[6.100525536],"iteration":56,"passed_time":0.2474101425,"remaining_time":4.093118672},
{"learn":[6.062568564],"iteration":57,"passed_time":0.2486485434,"remaining_time":4.038395308},
{"learn":[6.030559288],"iteration":58,"passed_time":0.2501103793,"remaining_time":3.989048592},
{"learn":[5.997931376],"iteration":59,"passed_time":0.251518033,"remaining_time":3.940449184},
{"learn":[5.964103835],"iteration":60,"passed_time":0.2527615119,"remaining_time":3.890869831},
{"learn":[5.933729724],"iteration":61,"passed_time":0.2542303824,"remaining_time":3.846259657},
{"learn":[5.901932711],"iteration":62,"passed_time":0.2555030823,"remaining_time":3.800101398},
{"learn":[5.873727795],"iteration":63,"passed_time":0.2566410086,"remaining_time":3.75337475},
{"learn":[5.846485734],"iteration":64,"passed_time":0.2575597012,"remaining_time":3.704897241},
{"learn":[5.820630862],"iteration":65,"passed_time":0.2588133575,"remaining_time":3.662601149},
{"learn":[5.793646238],"iteration":66,"passed_time":0.2600789286,"remaining_time":3.621696125},
{"learn":[5.765388646],"iteration":67,"passed_time":0.2612653973,"remaining_time":3.580872798},
{"learn":[5.747073912],"iteration":68,"passed_time":0.262330672,"remaining_time":3.539563125},
{"learn":[5.722315217],"iteration":69,"passed_time":0.2634521563,"remaining_time":3.500150076},
{"learn":[5.699970599],"iteration":70,"passed_time":0.2645357192,"remaining_time":3.461319481},
{"learn":[5.682732647],"iteration":71,"passed_time":0.2654967502,"remaining_time":3.421958113},
{"learn":[5.663525791],"iteration":72,"passed_time":0.2667904794,"remaining_time":3.387873622},
{"learn":[5.642381613],"iteration":73,"passed_time":0.2677520109,"remaining_time":3.350518407},
{"learn":[5.621404779],"iteration":74,"passed_time":0.2688556461,"remaining_time":3.315886301},
{"learn":[5.602460129],"iteration":75,"passed_time":0.2699280637,"remaining_time":3.281756984},
{"learn":[5.587337574],"iteration":76,"passed_time":0.2710732426,"remaining_time":3.24935848},
{"learn":[5.572393026],"iteration":77,"passed_time":0.2720263362,"remaining_time":3.215490795},
{"learn":[5.558425806],"iteration":78,"passed_time":0.2728607061,"remaining_time":3.181072282},
{"learn":[5.541518902],"iteration":79,"passed_time":0.2737523449,"remaining_time":3.148151966},
{"learn":[5.526157283],"iteration":80,"passed_time":0.2745853031,"remaining_time":3.11535671},
{"learn":[5.511746977],"iteration":81,"passed_time":0.2754888445,"remaining_time":3.08413121},
{"learn":[5.504975022],"iteration":82,"passed_time":0.2760166426,"remaining_time":3.049485076},
{"learn":[5.493980522],"iteration":83,"passed_time":0.2770239472,"remaining_time":3.020880186},
{"learn":[5.480745463],"iteration":84,"passed_time":0.2779797057,"remaining_time":2.992369773},
{"learn":[5.464052013],"iteration":85,"passed_time":0.2789700117,"remaining_time":2.964867333},
{"learn":[5.449143727],"iteration":86,"passed_time":0.2802111071,"remaining_time":2.940606215},
{"learn":[5.438255432],"iteration":87,"passed_time":0.281057887,"remaining_time":2.912781738},
{"learn":[5.425927931],"iteration":88,"passed_time":0.2818059198,"remaining_time":2.88455273},
{"learn":[5.412331217],"iteration":89,"passed_time":0.2826272467,"remaining_time":2.857675495},
{"learn":[5.400691499],"iteration":90,"passed_time":0.2834000559,"remaining_time":2.830886272},
{"learn":[5.391618744],"iteration":91,"passed_time":0.2845768005,"remaining_time":2.808649292},
{"learn":[5.380766572],"iteration":92,"passed_time":0.2855140074,"remaining_time":2.784529083},
{"learn":[5.372207183],"iteration":93,"passed_time":0.2863010647,"remaining_time":2.759454943},
{"learn":[5.362918837],"iteration":94,"passed_time":0.2870678018,"remaining_time":2.734698533},
{"learn":[5.348292324],"iteration":95,"passed_time":0.2877698408,"remaining_time":2.709832668},
{"learn":[5.339772295],"iteration":96,"passed_time":0.2886168522,"remaining_time":2.686814614},
{"learn":[5.331515983],"iteration":97,"passed_time":0.2893049071,"remaining_time":2.662785982},
{"learn":[5.323861644],"iteration":98,"passed_time":0.2900545674,"remaining_time":2.639789547},
{"learn":[5.313277281],"iteration":99,"passed_time":0.2907864905,"remaining_time":2.617078415},
{"learn":[5.30685627],"iteration":100,"passed_time":0.2915693941,"remaining_time":2.59525629},
{"learn":[5.29652059],"iteration":101,"passed_time":0.2924699701,"remaining_time":2.574882678},
{"learn":[5.288350766],"iteration":102,"passed_time":0.2933236879,"remaining_time":2.554479107},
{"learn":[5.27993346],"iteration":103,"passed_time":0.2941103802,"remaining_time":2.533874045},
{"learn":[5.271789139],"iteration":104,"passed_time":0.2948717584,"remaining_time":2.513430703},
{"learn":[5.262684686],"iteration":105,"passed_time":0.2956284026,"remaining_time":2.493318792},
{"learn":[5.251619772],"iteration":106,"passed_time":0.2963931984,"remaining_time":2.473636693},
{"learn":[5.241012171],"iteration":107,"passed_time":0.2971139624,"remaining_time":2.453941245},
{"learn":[5.232684032],"iteration":108,"passed_time":0.2978247122,"remaining_time":2.434512097},
{"learn":[5.224267141],"iteration":109,"passed_time":0.2984910506,"remaining_time":2.415063955},
{"learn":[5.216324968],"iteration":110,"passed_time":0.2992064573,"remaining_time":2.396347212},
{"learn":[5.211102527],"iteration":111,"passed_time":0.3000424953,"remaining_time":2.378908355},
{"learn":[5.206364257],"iteration":112,"passed_time":0.3008758423,"remaining_time":2.361742231},
{"learn":[5.196937641],"iteration":113,"passed_time":0.3016244078,"remaining_time":2.344203731},
{"learn":[5.190746047],"iteration":114,"passed_time":0.3024211151,"remaining_time":2.327327712},
{"learn":[5.181885213],"iteration":115,"passed_time":0.3033340539,"remaining_time":2.311614687},
{"learn":[5.178293568],"iteration":116,"passed_time":0.303939331,"remaining_time":2.293832729},
{"learn":[5.170991438],"iteration":117,"passed_time":0.3046824985,"remaining_time":2.277372574},
{"learn":[5.166257212],"iteration":118,"passed_time":0.3053159214,"remaining_time":2.26036409},
{"learn":[5.161421246],"iteration":119,"passed_time":0.3059785407,"remaining_time":2.243842632},
{"learn":[5.158223542],"iteration":120,"passed_time":0.3069178459,"remaining_time":2.229593277},
{"learn":[5.15470988],"iteration":121,"passed_time":0.3074525383,"remaining_time":2.212650234},
{"learn":[5.146388143],"iteration":122,"passed_time":0.3080905309,"remaining_time":2.196710533},
{"learn":[5.139529364],"iteration":123,"passed_time":0.3087774137,"remaining_time":2.181363019},
{"learn":[5.134276023],"iteration":124,"passed_time":0.3094577708,"remaining_time":2.166204395},
{"learn":[5.128536065],"iteration":125,"passed_time":0.3102023784,"remaining_time":2.15172126},
{"learn":[5.123300353],"iteration":126,"passed_time":0.3107049205,"remaining_time":2.135790516},
{"learn":[5.116200518],"iteration":127,"passed_time":0.3114892334,"remaining_time":2.122020403},
{"learn":[5.108728704],"iteration":128,"passed_time":0.3123686169,"remaining_time":2.109093529},
{"learn":[5.104075866],"iteration":129,"passed_time":0.3131259228,"remaining_time":2.095535022},
{"learn":[5.100317606],"iteration":130,"passed_time":0.3139559079,"remaining_time":2.082654076},
{"learn":[5.095814182],"iteration":131,"passed_time":0.3147883203,"remaining_time":2.069971682},
{"learn":[5.092146915],"iteration":132,"passed_time":0.315560148,"remaining_time":2.057072544},
{"learn":[5.085258329],"iteration":133,"passed_time":0.3163559878,"remaining_time":2.044509593},
{"learn":[5.079219421],"iteration":134,"passed_time":0.3170713699,"remaining_time":2.031605444},
{"learn":[5.076476829],"iteration":135,"passed_time":0.3176984015,"remaining_time":2.018319256},
{"learn":[5.072133867],"iteration":136,"passed_time":0.3183393902,"remaining_time":2.005305794},
{"learn":[5.067031564],"iteration":137,"passed_time":0.3189833935,"remaining_time":1.992490472},
{"learn":[5.061358312],"iteration":138,"passed_time":0.3196613724,"remaining_time":1.980060731},
{"learn":[5.056759124],"iteration":139,"passed_time":0.3204467374,"remaining_time":1.96845853},
{"learn":[5.050254],"iteration":140,"passed_time":0.321359758,"remaining_time":1.957787462},
{"learn":[5.048376474],"iteration":141,"passed_time":0.3218024849,"remaining_time":1.944412198},
{"learn":[5.042603751],"iteration":142,"passed_time":0.3225762928,"remaining_time":1.933201978},
{"learn":[5.037477349],"iteration":143,"passed_time":0.3232686403,"remaining_time":1.921652473},
{"learn":[5.03230489],"iteration":144,"passed_time":0.3238911912,"remaining_time":1.909841162},
{"learn":[5.025976187],"iteration":145,"passed_time":0.3246159508,"remaining_time":1.898780972},
{"learn":[5.01952451],"iteration":146,"passed_time":0.3253418088,"remaining_time":1.887867775},
{"learn":[5.017569424],"iteration":147,"passed_time":0.3260634794,"remaining_time":1.877068138},
{"learn":[5.008962367],"iteration":148,"passed_time":0.326805801,"remaining_time":1.866521723},
{"learn":[5.003880266],"iteration":149,"passed_time":0.3275040372,"remaining_time":1.855856211},
{"learn":[4.996387564],"iteration":150,"passed_time":0.3281977834,"remaining_time":1.845297471},
{"learn":[4.993361683],"iteration":151,"passed_time":0.3288886356,"remaining_time":1.834852388},
{"learn":[4.99005752],"iteration":152,"passed_time":0.3297263121,"remaining_time":1.825347623},
{"learn":[4.986908764],"iteration":153,"passed_time":0.3305048728,"remaining_time":1.815630665},
{"learn":[4.985207175],"iteration":154,"passed_time":0.3313638608,"remaining_time":1.806467499},
{"learn":[4.979003494],"iteration":155,"passed_time":0.3321436194,"remaining_time":1.796982146},
{"learn":[4.973142217],"iteration":156,"passed_time":0.332863106,"remaining_time":1.787284066},
{"learn":[4.967056696],"iteration":157,"passed_time":0.3335144725,"remaining_time":1.777336619},
{"learn":[4.961460696],"iteration":158,"passed_time":0.3345212858,"remaining_time":1.769386172},
{"learn":[4.954240363],"iteration":159,"passed_time":0.335231884,"remaining_time":1.759967391},
{"learn":[4.952320707],"iteration":160,"passed_time":0.3356307849,"remaining_time":1.749032475},
{"learn":[4.948337777],"iteration":161,"passed_time":0.3363659798,"remaining_time":1.739967229},
{"learn":[4.943228639],"iteration":162,"passed_time":0.3370712766,"remaining_time":1.730850666},
{"learn":[4.938545759],"iteration":163,"passed_time":0.3377257367,"remaining_time":1.721577536},
{"learn":[4.935330572],"iteration":164,"passed_time":0.3385351284,"remaining_time":1.713192922},
{"learn":[4.932051543],"iteration":165,"passed_time":0.3395438258,"remaining_time":1.705900908},
{"learn":[4.928964153],"iteration":166,"passed_time":0.3403284067,"remaining_time":1.697566244},
{"learn":[4.922860227],"iteration":167,"passed_time":0.3410613854,"remaining_time":1.689065909},
{"learn":[4.917668772],"iteration":168,"passed_time":0.341764562,"remaining_time":1.680510953},
{"learn":[4.910365386],"iteration":169,"passed_time":0.3425964333,"remaining_time":1.672676704},
{"learn":[4.906457206],"iteration":170,"passed_time":0.3434427322,"remaining_time":1.664994298},
{"learn":[4.901996508],"iteration":171,"passed_time":0.3441041816,"remaining_time":1.656501525},
{"learn":[4.896816173],"iteration":172,"passed_time":0.3448963709,"remaining_time":1.64872427},
{"learn":[4.891123132],"iteration":173,"passed_time":0.3458522649,"remaining_time":1.64180443},
{"learn":[4.887630202],"iteration":174,"passed_time":0.3465893896,"remaining_time":1.633921408},
{"learn":[4.885259712],"iteration":175,"passed_time":0.3472961526,"remaining_time":1.625977442},
{"learn":[4.880659728],"iteration":176,"passed_time":0.3482270572,"remaining_time":1.619157447},
{"learn":[4.877299723],"iteration":177,"passed_time":0.3489828263,"remaining_time":1.61159485},
{"learn":[4.874038772],"iteration":178,"passed_time":0.3497255824,"remaining_time":1.604048621},
{"learn":[4.86943698],"iteration":179,"passed_time":0.3504879244,"remaining_time":1.596667211},
{"learn":[4.861268711],"iteration":180,"passed_time":0.3511994023,"remaining_time":1.589128787},
{"learn":[4.858673056],"iteration":181,"passed_time":0.3519365746,"remaining_time":1.581780868},
{"learn":[4.854036207],"iteration":182,"passed_time":0.3527034192,"remaining_time":1.574637669},
{"learn":[4.85130244],"iteration":183,"passed_time":0.3534156217,"remaining_time":1.567321453},
{"learn":[4.847510084],"iteration":184,"passed_time":0.3541328009,"remaining_time":1.560098555},
{"learn":[4.845691673],"iteration":185,"passed_time":0.3547995616,"remaining_time":1.552724963},
{"learn":[4.842058646],"iteration":186,"passed_time":0.3554449443,"remaining_time":1.545330159},
{"learn":[4.838623675],"iteration":187,"passed_time":0.3561737224,"remaining_time":1.538367354},
{"learn":[4.834602161],"iteration":188,"passed_time":0.3569521825,"remaining_time":1.531683704},
{"learn":[4.830858976],"iteration":189,"passed_time":0.3576671616,"remaining_time":1.524791584},
{"learn":[4.827590511],"iteration":190,"passed_time":0.3582958144,"remaining_time":1.517598502},
{"learn":[4.822246226],"iteration":191,"passed_time":0.3590035309,"remaining_time":1.510806526},
{"learn":[4.816686395],"iteration":192,"passed_time":0.3597261353,"remaining_time":1.504139851},
{"learn":[4.814797121],"iteration":193,"passed_time":0.3605531316,"remaining_time":1.497968165},
{"learn":[4.811639392],"iteration":194,"passed_time":0.361409641,"remaining_time":1.491973133},
{"learn":[4.804813432],"iteration":195,"passed_time":0.3622852933,"remaining_time":1.48610906},
{"learn":[4.80251613],"iteration":196,"passed_time":0.3635530987,"remaining_time":1.481894103},
{"learn":[4.800087884],"iteration":197,"passed_time":0.364397743,"remaining_time":1.475994898},
{"learn":[4.794773135],"iteration":198,"passed_time":0.3652639572,"remaining_time":1.470233315},
{"learn":[4.791664833],"iteration":199,"passed_time":0.3660079231,"remaining_time":1.464031692},
{"learn":[4.785989873],"iteration":200,"passed_time":0.3668101205,"remaining_time":1.458115852},
{"learn":[4.782387142],"iteration":201,"passed_time":0.3677070513,"remaining_time":1.452624886},
{"learn":[4.778623704],"iteration":202,"passed_time":0.3686713091,"remaining_time":1.447443514},
{"learn":[4.775772178],"iteration":203,"passed_time":0.3694105241,"remaining_time":1.441425378},
{"learn":[4.77023101],"iteration":204,"passed_time":0.3701172211,"remaining_time":1.435332638},
{"learn":[4.764496689],"iteration":205,"passed_time":0.3709879675,"remaining_time":1.429924496},
{"learn":[4.763138716],"iteration":206,"passed_time":0.3717033599,"remaining_time":1.423965046},
{"learn":[4.758053283],"iteration":207,"passed_time":0.3723973103,"remaining_time":1.417974374},
{"learn":[4.755063788],"iteration":208,"passed_time":0.3731237641,"remaining_time":1.412157404},
{"learn":[4.752465267],"iteration":209,"passed_time":0.373810521,"remaining_time":1.406239579},
{"learn":[4.748067377],"iteration":210,"passed_time":0.3745961907,"remaining_time":1.400741206},
{"learn":[4.744163298],"iteration":211,"passed_time":0.3754591571,"remaining_time":1.395574603},
{"learn":[4.736670896],"iteration":212,"passed_time":0.376248741,"remaining_time":1.390177273},
{"learn":[4.73349255],"iteration":213,"passed_time":0.3770840152,"remaining_time":1.384990822},
{"learn":[4.731864595],"iteration":214,"passed_time":0.377850218,"remaining_time":1.379592656},
{"learn":[4.728398311],"iteration":215,"passed_time":0.3785811908,"remaining_time":1.374109507},
{"learn":[4.723865975],"iteration":216,"passed_time":0.3793239181,"remaining_time":1.368712571},
{"learn":[4.723483365],"iteration":217,"passed_time":0.3800335829,"remaining_time":1.363239733},
{"learn":[4.72095416],"iteration":218,"passed_time":0.3807424608,"remaining_time":1.357807588},
{"learn":[4.716173382],"iteration":219,"passed_time":0.381377779,"remaining_time":1.35215758},
{"learn":[4.710563974],"iteration":220,"passed_time":0.3820382396,"remaining_time":1.346641578},
{"learn":[4.707160263],"iteration":221,"passed_time":0.3827414232,"remaining_time":1.341319042},
{"learn":[4.70408351],"iteration":222,"passed_time":0.3833872296,"remaining_time":1.335838015},
{"learn":[4.702501831],"iteration":223,"passed_time":0.384165071,"remaining_time":1.330857567},
{"learn":[4.700269738],"iteration":224,"passed_time":0.3850344786,"remaining_time":1.326229871},
{"learn":[4.695346302],"iteration":225,"passed_time":0.3858308565,"remaining_time":1.321385323},
{"learn":[4.689769299],"iteration":226,"passed_time":0.3865443195,"remaining_time":1.316294093},
{"learn":[4.687919514],"iteration":227,"passed_time":0.3871876473,"remaining_time":1.311003788},
{"learn":[4.682982074],"iteration":228,"passed_time":0.3878918695,"remaining_time":1.305959089},
{"learn":[4.679578702],"iteration":229,"passed_time":0.3886135976,"remaining_time":1.30101074},
{"learn":[4.675751423],"iteration":230,"passed_time":0.3893197412,"remaining_time":1.296047104},
{"learn":[4.672710726],"iteration":231,"passed_time":0.3903211331,"remaining_time":1.292097544},
{"learn":[4.6690533],"iteration":232,"passed_time":0.3913474709,"remaining_time":1.288255408},
{"learn":[4.667595702],"iteration":233,"passed_time":0.3920734191,"remaining_time":1.283454013},
{"learn":[4.664241291],"iteration":234,"passed_time":0.3930310564,"remaining_time":1.279441524},
{"learn":[4.662246999],"iteration":235,"passed_time":0.393749101,"remaining_time":1.274679293},
{"learn":[4.658668443],"iteration":236,"passed_time":0.3945784068,"remaining_time":1.270309386},
{"learn":[4.658017572],"iteration":237,"passed_time":0.3952823649,"remaining_time":1.265567908},
{"learn":[4.657656705],"iteration":238,"passed_time":0.3958918018,"remaining_time":1.260559252},
{"learn":[4.653242871],"iteration":239,"passed_time":0.3966726013,"remaining_time":1.256129904},
{"learn":[4.6507302],"iteration":240,"passed_time":0.3974131623,"remaining_time":1.251604109},
{"learn":[4.647671336],"iteration":241,"passed_time":0.3981455254,"remaining_time":1.247083918},
{"learn":[4.645506007],"iteration":242,"passed_time":0.3988157389,"remaining_time":1.242401293},
{"learn":[4.641297906],"iteration":243,"passed_time":0.3994987734,"remaining_time":1.237791282},
{"learn":[4.63798107],"iteration":244,"passed_time":0.4001784934,"remaining_time":1.233203112},
{"learn":[4.635062318],"iteration":245,"passed_time":0.4008524745,"remaining_time":1.228629129},
{"learn":[4.631606017],"iteration":246,"passed_time":0.4015289611,"remaining_time":1.224094363},
{"learn":[4.630215494],"iteration":247,"passed_time":0.4021618052,"remaining_time":1.219458377},
{"learn":[4.62729814],"iteration":248,"passed_time":0.4030268814,"remaining_time":1.215554972},
{"learn":[4.624691756],"iteration":249,"passed_time":0.4041176563,"remaining_time":1.212352969},
{"learn":[4.621840053],"iteration":250,"passed_time":0.4049819345,"remaining_time":1.208491908},
{"learn":[4.619602091],"iteration":251,"passed_time":0.4060167662,"remaining_time":1.205160878},
{"learn":[4.613584029],"iteration":252,"passed_time":0.4068080017,"remaining_time":1.201128764},
{"learn":[4.6119388],"iteration":253,"passed_time":0.4074974814,"remaining_time":1.196823312},
{"learn":[4.60870702],"iteration":254,"passed_time":0.4081754581,"remaining_time":1.192512613},
{"learn":[4.604771557],"iteration":255,"passed_time":0.4088925374,"remaining_time":1.188343937},
{"learn":[4.604231277],"iteration":256,"passed_time":0.4094999343,"remaining_time":1.183885024},
{"learn":[4.600750354],"iteration":257,"passed_time":0.4101771855,"remaining_time":1.179656867},
{"learn":[4.596488253],"iteration":258,"passed_time":0.4110106749,"remaining_time":1.175903128},
{"learn":[4.59470784],"iteration":259,"passed_time":0.4117271317,"remaining_time":1.171838759},
{"learn":[4.588818005],"iteration":260,"passed_time":0.4124907461,"remaining_time":1.167933568},
{"learn":[4.585054174],"iteration":261,"passed_time":0.4131627397,"remaining_time":1.163794282},
{"learn":[4.581471435],"iteration":262,"passed_time":0.4138911709,"remaining_time":1.159839517},
{"learn":[4.577555199],"iteration":263,"passed_time":0.4145603481,"remaining_time":1.155744001},
{"learn":[4.57457145],"iteration":264,"passed_time":0.4153352421,"remaining_time":1.151967558},
{"learn":[4.573029224],"iteration":265,"passed_time":0.4161831743,"remaining_time":1.148415225},
{"learn":[4.571326203],"iteration":266,"passed_time":0.4168698828,"remaining_time":1.14444054},
{"learn":[4.571019224],"iteration":267,"passed_time":0.4175484559,"remaining_time":1.14046817},
{"learn":[4.565766631],"iteration":268,"passed_time":0.4184007896,"remaining_time":1.13699248},
{"learn":[4.563383471],"iteration":269,"passed_time":0.4191460421,"remaining_time":1.133246706},
{"learn":[4.558165805],"iteration":270,"passed_time":0.4199537147,"remaining_time":1.129690989},
{"learn":[4.55629209],"iteration":271,"passed_time":0.4207807805,"remaining_time":1.126207383},
{"learn":[4.549383848],"iteration":272,"passed_time":0.4216780337,"remaining_time":1.122930148},
{"learn":[4.546227503],"iteration":273,"passed_time":0.4225835483,"remaining_time":1.119692176},
{"learn":[4.540620977],"iteration":274,"passed_time":0.4232850631,"remaining_time":1.115933348},
{"learn":[4.532898237],"iteration":275,"passed_time":0.4239900682,"remaining_time":1.112205831},
{"learn":[4.529757367],"iteration":276,"passed_time":0.4247692365,"remaining_time":1.108693711},
{"learn":[4.52579294],"iteration":277,"passed_time":0.425472569,"remaining_time":1.105004298},
{"learn":[4.521572155],"iteration":278,"passed_time":0.4261546202,"remaining_time":1.101281295},
{"learn":[4.518818099],"iteration":279,"passed_time":0.4267953019,"remaining_time":1.097473633},
{"learn":[4.514012334],"iteration":280,"passed_time":0.4274472257,"remaining_time":1.093717278},
{"learn":[4.508331416],"iteration":281,"passed_time":0.4281108551,"remaining_time":1.090012745},
{"learn":[4.506038537],"iteration":282,"passed_time":0.4287758909,"remaining_time":1.086333264},
{"learn":[4.505805643],"iteration":283,"passed_time":0.4295108628,"remaining_time":1.08285133},
{"learn":[4.501550352],"iteration":284,"passed_time":0.4303115801,"remaining_time":1.079553613},
{"learn":[4.494692643],"iteration":285,"passed_time":0.4309922028,"remaining_time":1.075973541},
{"learn":[4.489330245],"iteration":286,"passed_time":0.4316675626,"remaining_time":1.0724006},
{"learn":[4.484826955],"iteration":287,"passed_time":0.432286953,"remaining_time":1.068709412},
{"learn":[4.478285428],"iteration":288,"passed_time":0.4331632206,"remaining_time":1.065671453},
{"learn":[4.475311671],"iteration":289,"passed_time":0.4339664344,"remaining_time":1.062469546},
{"learn":[4.471581298],"iteration":290,"passed_time":0.4346967025,"remaining_time":1.059106399},
{"learn":[4.469164956],"iteration":291,"passed_time":0.4355528829,"remaining_time":1.056066579},
{"learn":[4.462068024],"iteration":292,"passed_time":0.4364681626,"remaining_time":1.05318427},
{"learn":[4.458540976],"iteration":293,"passed_time":0.4372157322,"remaining_time":1.049912609},
{"learn":[4.455757458],"iteration":294,"passed_time":0.4380400583,"remaining_time":1.046841495},
{"learn":[4.453027414],"iteration":295,"passed_time":0.4387324466,"remaining_time":1.043471765},
{"learn":[4.450659338],"iteration":296,"passed_time":0.4395742226,"remaining_time":1.040473665},
{"learn":[4.444696901],"iteration":297,"passed_time":0.4403553929,"remaining_time":1.037347268},
{"learn":[4.442052813],"iteration":298,"passed_time":0.4410547889,"remaining_time":1.03404484},
{"learn":[4.440036756],"iteration":299,"passed_time":0.4418220434,"remaining_time":1.030918101},
{"learn":[4.435017051],"iteration":300,"passed_time":0.4425391489,"remaining_time":1.027690582},
{"learn":[4.429962125],"iteration":301,"passed_time":0.4432862636,"remaining_time":1.024549046},
{"learn":[4.427666256],"iteration":302,"passed_time":0.4439868372,"remaining_time":1.021316256},
{"learn":[4.425030004],"iteration":303,"passed_time":0.4446972811,"remaining_time":1.018122723},
{"learn":[4.422588771],"iteration":304,"passed_time":0.4454198759,"remaining_time":1.01497316},
{"learn":[4.418936667],"iteration":305,"passed_time":0.4461287991,"remaining_time":1.011808453},
{"learn":[4.416887976],"iteration":306,"passed_time":0.4472210268,"remaining_time":1.009524989},
{"learn":[4.413773354],"iteration":307,"passed_time":0.4482191643,"remaining_time":1.007037863},
{"learn":[4.411129391],"iteration":308,"passed_time":0.4491722237,"remaining_time":1.004459568},
{"learn":[4.40850819],"iteration":309,"passed_time":0.449939325,"remaining_time":1.001477853},
{"learn":[4.404880292],"iteration":310,"passed_time":0.4507835978,"remaining_time":0.998681347},
{"learn":[4.404593827],"iteration":311,"passed_time":0.4517126928,"remaining_time":0.9960843994},
{"learn":[4.402139942],"iteration":312,"passed_time":0.4525339299,"remaining_time":0.9932613733},
{"learn":[4.400284725],"iteration":313,"passed_time":0.4533729179,"remaining_time":0.9904898779},
{"learn":[4.395805521],"iteration":314,"passed_time":0.4541361511,"remaining_time":0.9875659159},
{"learn":[4.392838833],"iteration":315,"passed_time":0.4550062146,"remaining_time":0.9848868697},
{"learn":[4.389213061],"iteration":316,"passed_time":0.4557142716,"remaining_time":0.9818701813},
{"learn":[4.3861981],"iteration":317,"passed_time":0.4565347123,"remaining_time":0.979109037},
{"learn":[4.385054234],"iteration":318,"passed_time":0.45728539,"remaining_time":0.9762111304},
{"learn":[4.379364607],"iteration":319,"passed_time":0.458052045,"remaining_time":0.9733605955},
{"learn":[4.378387619],"iteration":320,"passed_time":0.4588839768,"remaining_time":0.9706611223},
{"learn":[4.375816727],"iteration":321,"passed_time":0.4597060016,"remaining_time":0.9679523884},
{"learn":[4.374600202],"iteration":322,"passed_time":0.4604009837,"remaining_time":0.9649890586},
{"learn":[4.37098897],"iteration":323,"passed_time":0.4612662548,"remaining_time":0.9623950255},
{"learn":[4.367418484],"iteration":324,"passed_time":0.4621132274,"remaining_time":0.9597736262},
{"learn":[4.363584638],"iteration":325,"passed_time":0.4629003066,"remaining_time":0.9570392841},
{"learn":[4.360770706],"iteration":326,"passed_time":0.4635744907,"remaining_time":0.9540845022},
{"learn":[4.358675808],"iteration":327,"passed_time":0.464360274,"remaining_time":0.9513722688},
{"learn":[4.354228195],"iteration":328,"passed_time":0.4651782948,"remaining_time":0.9487374948},
{"learn":[4.353773425],"iteration":329,"passed_time":0.4660141719,"remaining_time":0.9461499854},
{"learn":[4.351648009],"iteration":330,"passed_time":0.4668199292,"remaining_time":0.9435121832},
{"learn":[4.348209927],"iteration":331,"passed_time":0.4675883881,"remaining_time":0.9408103713},
{"learn":[4.345852733],"iteration":332,"passed_time":0.4682953638,"remaining_time":0.9379970201},
{"learn":[4.34237339],"iteration":333,"passed_time":0.4689899648,"remaining_time":0.9351716065},
{"learn":[4.340814362],"iteration":334,"passed_time":0.4697350434,"remaining_time":0.932459116},
{"learn":[4.339707068],"iteration":335,"passed_time":0.470555691,"remaining_time":0.929907675},
{"learn":[4.335430786],"iteration":336,"passed_time":0.4712235755,"remaining_time":0.927065966},
{"learn":[4.33521887],"iteration":337,"passed_time":0.4719287465,"remaining_time":0.9243101484},
{"learn":[4.328507238],"iteration":338,"passed_time":0.4727331163,"remaining_time":0.9217598521},
{"learn":[4.326140732],"iteration":339,"passed_time":0.4733705708,"remaining_time":0.9188958139},
{"learn":[4.323785636],"iteration":340,"passed_time":0.4741335411,"remaining_time":0.9162874006},
{"learn":[4.320632534],"iteration":341,"passed_time":0.4750686447,"remaining_time":0.9140209597},
{"learn":[4.31973724],"iteration":342,"passed_time":0.4758834026,"remaining_time":0.9115317653},
{"learn":[4.318000924],"iteration":343,"passed_time":0.4766750158,"remaining_time":0.9090081696},
{"learn":[4.312713628],"iteration":344,"passed_time":0.4774437871,"remaining_time":0.906451248},
{"learn":[4.308220789],"iteration":345,"passed_time":0.4782871898,"remaining_time":0.9040457287},
{"learn":[4.305890947],"iteration":346,"passed_time":0.4790801506,"remaining_time":0.9015542892},
{"learn":[4.305137856],"iteration":347,"passed_time":0.4798305727,"remaining_time":0.8989929121},
{"learn":[4.304787172],"iteration":348,"passed_time":0.4807593533,"remaining_time":0.8967746103},
{"learn":[4.30350134],"iteration":349,"passed_time":0.4815305462,"remaining_time":0.8942710143},
{"learn":[4.30293809],"iteration":350,"passed_time":0.482292821,"remaining_time":0.8917608},
{"learn":[4.299548459],"iteration":351,"passed_time":0.4830773685,"remaining_time":0.8893015192},
{"learn":[4.294768408],"iteration":352,"passed_time":0.4839461496,"remaining_time":0.8870061156},
{"learn":[4.294581479],"iteration":353,"passed_time":0.4847985467,"remaining_time":0.8846888734},
{"learn":[4.292551604],"iteration":354,"passed_time":0.4855378807,"remaining_time":0.8821744593},
{"learn":[4.288628894],"iteration":355,"passed_time":0.4862882648,"remaining_time":0.8796900071},
{"learn":[4.287802767],"iteration":356,"passed_time":0.4870880042,"remaining_time":0.8773041645},
{"learn":[4.284566905],"iteration":357,"passed_time":0.487938863,"remaining_time":0.8750188548},
{"learn":[4.27890232],"iteration":358,"passed_time":0.4887418906,"remaining_time":0.8726561333},
{"learn":[4.276938023],"iteration":359,"passed_time":0.4895558678,"remaining_time":0.8703215427},
{"learn":[4.273425094],"iteration":360,"passed_time":0.4904395688,"remaining_time":0.8681187935},
{"learn":[4.269726505],"iteration":361,"passed_time":0.491165347,"remaining_time":0.8656450038},
{"learn":[4.265565857],"iteration":362,"passed_time":0.4920860585,"remaining_time":0.8635229182},
{"learn":[4.262117173],"iteration":363,"passed_time":0.4929986984,"remaining_time":0.8613933301},
{"learn":[4.259185148],"iteration":364,"passed_time":0.4938556591,"remaining_time":0.8591735439},
{"learn":[4.257668507],"iteration":365,"passed_time":0.4945618318,"remaining_time":0.8567000038},
{"learn":[4.253432436],"iteration":366,"passed_time":0.4954481869,"remaining_time":0.8545468729},
{"learn":[4.250216667],"iteration":367,"passed_time":0.4963249201,"remaining_time":0.8523841019},
{"learn":[4.24514828],"iteration":368,"passed_time":0.4972523773,"remaining_time":0.8503150408},
{"learn":[4.244015772],"iteration":369,"passed_time":0.4979527678,"remaining_time":0.8478655235},
{"learn":[4.240329192],"iteration":370,"passed_time":0.4987953226,"remaining_time":0.8456664634},
{"learn":[4.236718014],"iteration":371,"passed_time":0.499774263,"remaining_time":0.8437049386},
{"learn":[4.233495944],"iteration":372,"passed_time":0.5007205549,"remaining_time":0.8416938014},
{"learn":[4.230357491],"iteration":373,"passed_time":0.5018041324,"remaining_time":0.8399181468},
{"learn":[4.227381215],"iteration":374,"passed_time":0.5027058867,"remaining_time":0.8378431446},
{"learn":[4.226169067],"iteration":375,"passed_time":0.5034574876,"remaining_time":0.8355251921},
{"learn":[4.225963861],"iteration":376,"passed_time":0.5042879371,"remaining_time":0.8333458483},
{"learn":[4.224346548],"iteration":377,"passed_time":0.5050806189,"remaining_time":0.8311114945},
{"learn":[4.222595381],"iteration":378,"passed_time":0.5060439136,"remaining_time":0.8291643017},
{"learn":[4.219700938],"iteration":379,"passed_time":0.5068954571,"remaining_time":0.8270399563},
{"learn":[4.216356207],"iteration":380,"passed_time":0.5076017826,"remaining_time":0.8246863607},
{"learn":[4.214326494],"iteration":381,"passed_time":0.5083423033,"remaining_time":0.8223967106},
{"learn":[4.212901398],"iteration":382,"passed_time":0.5091061207,"remaining_time":0.8201526801},
{"learn":[4.211331091],"iteration":383,"passed_time":0.509886924,"remaining_time":0.8179436073},
{"learn":[4.208624791],"iteration":384,"passed_time":0.5108055499,"remaining_time":0.8159621122},
{"learn":[4.204659106],"iteration":385,"passed_time":0.5116733516,"remaining_time":0.8139052795},
{"learn":[4.202968852],"iteration":386,"passed_time":0.5125106742,"remaining_time":0.8118063134},
{"learn":[4.197261935],"iteration":387,"passed_time":0.5133747202,"remaining_time":0.809756002},
{"learn":[4.196934403],"iteration":388,"passed_time":0.514116866,"remaining_time":0.8075203217},
{"learn":[4.192479929],"iteration":389,"passed_time":0.5150169101,"remaining_time":0.8055392696},
{"learn":[4.190243116],"iteration":390,"passed_time":0.5157479938,"remaining_time":0.8033005837},
{"learn":[4.185852431],"iteration":391,"passed_time":0.5168071474,"remaining_time":0.8015784327},
{"learn":[4.180967944],"iteration":392,"passed_time":0.5179050057,"remaining_time":0.7999194362},
{"learn":[4.178283162],"iteration":393,"passed_time":0.5188655565,"remaining_time":0.7980520996},
{"learn":[4.176341157],"iteration":394,"passed_time":0.5197758807,"remaining_time":0.7961124249},
{"learn":[4.176041504],"iteration":395,"passed_time":0.5206159572,"remaining_time":0.7940708035},
{"learn":[4.175564513],"iteration":396,"passed_time":0.5212827363,"remaining_time":0.7917720151},
{"learn":[4.170830274],"iteration":397,"passed_time":0.5221154109,"remaining_time":0.7897323552},
{"learn":[4.167804808],"iteration":398,"passed_time":0.5228715822,"remaining_time":0.7875835111},
{"learn":[4.165860548],"iteration":399,"passed_time":0.5236191069,"remaining_time":0.7854286603},
{"learn":[4.160950571],"iteration":400,"passed_time":0.5242698584,"remaining_time":0.7831362723},
{"learn":[4.158544115],"iteration":401,"passed_time":0.5249744598,"remaining_time":0.7809321567},
{"learn":[4.154448767],"iteration":402,"passed_time":0.525862673,"remaining_time":0.7790074834},
{"learn":[4.15197457],"iteration":403,"passed_time":0.526738016,"remaining_time":0.7770689543},
{"learn":[4.149562679],"iteration":404,"passed_time":0.5275514589,"remaining_time":0.7750447359},
{"learn":[4.149327961],"iteration":405,"passed_time":0.5283903951,"remaining_time":0.77306378},
{"learn":[4.147444889],"iteration":406,"passed_time":0.5293060099,"remaining_time":0.7712001569},
{"learn":[4.147254809],"iteration":407,"passed_time":0.5300366952,"remaining_time":0.7690728519},
{"learn":[4.144589165],"iteration":408,"passed_time":0.530727876,"remaining_time":0.7668952927},
{"learn":[4.141691034],"iteration":409,"passed_time":0.5316171566,"remaining_time":0.7650100546},
{"learn":[4.138893468],"iteration":410,"passed_time":0.5323858374,"remaining_time":0.7629568326},
{"learn":[4.136964597],"iteration":411,"passed_time":0.5331320095,"remaining_time":0.7608777222},
{"learn":[4.133773523],"iteration":412,"passed_time":0.5338112542,"remaining_time":0.7587099424},
{"learn":[4.131363444],"iteration":413,"passed_time":0.5344644139,"remaining_time":0.7565124312},
{"learn":[4.130228592],"iteration":414,"passed_time":0.5351362962,"remaining_time":0.7543487549},
{"learn":[4.12884186],"iteration":415,"passed_time":0.5358146029,"remaining_time":0.7522012695},
{"learn":[4.12413494],"iteration":416,"passed_time":0.5364916392,"remaining_time":0.7500590543},
{"learn":[4.119422508],"iteration":417,"passed_time":0.5371883454,"remaining_time":0.7479512369},
{"learn":[4.117038244],"iteration":418,"passed_time":0.537909481,"remaining_time":0.7458840297},
{"learn":[4.116067631],"iteration":419,"passed_time":0.5387038646,"remaining_time":0.7439243844},
{"learn":[4.110343455],"iteration":420,"passed_time":0.5393366549,"remaining_time":0.7417480361},
{"learn":[4.105604544],"iteration":421,"passed_time":0.5400553502,"remaining_time":0.7396966645},
{"learn":[4.103390131],"iteration":422,"passed_time":0.5409067432,"remaining_time":0.7378326024},
{"learn":[4.096724402],"iteration":423,"passed_time":0.5419836373,"remaining_time":0.7362796582},
{"learn":[4.093431279],"iteration":424,"passed_time":0.5428286079,"remaining_time":0.7344151754},
{"learn":[4.091412744],"iteration":425,"passed_time":0.5435341335,"remaining_time":0.7323675883},
{"learn":[4.091192901],"iteration":426,"passed_time":0.5443188057,"remaining_time":0.7304324957},
{"learn":[4.088994581],"iteration":427,"passed_time":0.5451470913,"remaining_time":0.7285610659},
{"learn":[4.087845355],"iteration":428,"passed_time":0.5459735284,"remaining_time":0.726692039},
{"learn":[4.083650279],"iteration":429,"passed_time":0.5466727149,"remaining_time":0.7246591802},
{"learn":[4.079840652],"iteration":430,"passed_time":0.5474840495,"remaining_time":0.7227805665},
{"learn":[4.075707828],"iteration":431,"passed_time":0.5482603437,"remaining_time":0.7208608223},
{"learn":[4.071345409],"iteration":432,"passed_time":0.5491263157,"remaining_time":0.7190637898},
{"learn":[4.067460475],"iteration":433,"passed_time":0.549858995,"remaining_time":0.7170972147},
{"learn":[4.064914749],"iteration":434,"passed_time":0.5505236063,"remaining_time":0.7150479024},
{"learn":[4.063823175],"iteration":435,"passed_time":0.5512734139,"remaining_time":0.7131151501},
{"learn":[4.058898471],"iteration":436,"passed_time":0.5519555872,"remaining_time":0.7111006764},
{"learn":[4.054120355],"iteration":437,"passed_time":0.5526480146,"remaining_time":0.7091054434},
{"learn":[4.052715901],"iteration":438,"passed_time":0.5532964986,"remaining_time":0.7070599902},
{"learn":[4.052114167],"iteration":439,"passed_time":0.5539568088,"remaining_time":0.7050359384},
{"learn":[4.051377267],"iteration":440,"passed_time":0.5547160154,"remaining_time":0.7031434299},
{"learn":[4.049275336],"iteration":441,"passed_time":0.5554350161,"remaining_time":0.7012052918},
{"learn":[4.047099198],"iteration":442,"passed_time":0.5562520124,"remaining_time":0.6993958711},
{"learn":[4.044348685],"iteration":443,"passed_time":0.5570645764,"remaining_time":0.6975853704},
{"learn":[4.042822379],"iteration":444,"passed_time":0.5578500884,"remaining_time":0.6957456159},
{"learn":[4.041258611],"iteration":445,"passed_time":0.5587319309,"remaining_time":0.6940302461},
{"learn":[4.040044254],"iteration":446,"passed_time":0.559511435,"remaining_time":0.692191999},
{"learn":[4.036860137],"iteration":447,"passed_time":0.5603148756,"remaining_time":0.6903879717},
{"learn":[4.036372284],"iteration":448,"passed_time":0.5609754123,"remaining_time":0.6884130338},
{"learn":[4.03368231],"iteration":449,"passed_time":0.5616031101,"remaining_time":0.6864038013},
{"learn":[4.032439519],"iteration":450,"passed_time":0.5622584928,"remaining_time":0.684434396},
{"learn":[4.032008634],"iteration":451,"passed_time":0.5629563168,"remaining_time":0.6825222601},
{"learn":[4.030034932],"iteration":452,"passed_time":0.5636274507,"remaining_time":0.6805832572},
{"learn":[4.028173412],"iteration":453,"passed_time":0.5643511816,"remaining_time":0.6787130951},
{"learn":[4.023806097],"iteration":454,"passed_time":0.5651358941,"remaining_time":0.676921016},
{"learn":[4.020239186],"iteration":455,"passed_time":0.5659238591,"remaining_time":0.6751372354},
{"learn":[4.017384838],"iteration":456,"passed_time":0.566753736,"remaining_time":0.6734076119},
{"learn":[4.016468229],"iteration":457,"passed_time":0.5675561729,"remaining_time":0.6716494448},
{"learn":[4.014530169],"iteration":458,"passed_time":0.5682848827,"remaining_time":0.6698085437},
{"learn":[4.012884822],"iteration":459,"passed_time":0.5689819444,"remaining_time":0.667935326},
{"learn":[4.008924707],"iteration":460,"passed_time":0.5698048089,"remaining_time":0.6662142994},
{"learn":[4.008286778],"iteration":461,"passed_time":0.5705678959,"remaining_time":0.6644275498},
{"learn":[4.006444202],"iteration":462,"passed_time":0.57150814,"remaining_time":0.6628506937},
{"learn":[4.003284363],"iteration":463,"passed_time":0.5722474486,"remaining_time":0.6610444665},
{"learn":[3.999811484],"iteration":464,"passed_time":0.5729774381,"remaining_time":0.6592321062},
{"learn":[3.997483319],"iteration":465,"passed_time":0.5738982318,"remaining_time":0.6576430382},
{"learn":[3.99708333],"iteration":466,"passed_time":0.5747288702,"remaining_time":0.6559539354},
{"learn":[3.995860263],"iteration":467,"passed_time":0.5754598081,"remaining_time":0.6541551665},
{"learn":[3.994131111],"iteration":468,"passed_time":0.5761225072,"remaining_time":0.6522836915},
{"learn":[3.993125499],"iteration":469,"passed_time":0.5768038921,"remaining_time":0.6504384316},
{"learn":[3.992954084],"iteration":470,"passed_time":0.5775114013,"remaining_time":0.648627455},
{"learn":[3.990635743],"iteration":471,"passed_time":0.5782785357,"remaining_time":0.6468878535},
{"learn":[3.986678254],"iteration":472,"passed_time":0.5790144468,"remaining_time":0.645117576},
{"learn":[3.986393291],"iteration":473,"passed_time":0.5796710999,"remaining_time":0.6432637101},
{"learn":[3.986152671],"iteration":474,"passed_time":0.58036668,"remaining_time":0.6414579095},
{"learn":[3.985596662],"iteration":475,"passed_time":0.5809916689,"remaining_time":0.6395790641},
{"learn":[3.983853457],"iteration":476,"passed_time":0.5817165406,"remaining_time":0.637814991},
{"learn":[3.983263928],"iteration":477,"passed_time":0.5823919632,"remaining_time":0.6360012653},
{"learn":[3.980067202],"iteration":478,"passed_time":0.5831764566,"remaining_time":0.6343109267},
{"learn":[3.978115407],"iteration":479,"passed_time":0.5840506423,"remaining_time":0.6327215292},
{"learn":[3.972661644],"iteration":480,"passed_time":0.5848202351,"remaining_time":0.6310222495},
{"learn":[3.969938254],"iteration":481,"passed_time":0.5854726516,"remaining_time":0.6292008995},
{"learn":[3.968211434],"iteration":482,"passed_time":0.5863605275,"remaining_time":0.6276364238},
{"learn":[3.966113368],"iteration":483,"passed_time":0.5878898399,"remaining_time":0.6267585897},
{"learn":[3.962246044],"iteration":484,"passed_time":0.5886649082,"remaining_time":0.6250771706},
{"learn":[3.961319703],"iteration":485,"passed_time":0.5893525625,"remaining_time":0.6233070311},
{"learn":[3.96078191],"iteration":486,"passed_time":0.5900181394,"remaining_time":0.6215180812},
{"learn":[3.958913633],"iteration":487,"passed_time":0.5906538967,"remaining_time":0.619702449},
{"learn":[3.957428286],"iteration":488,"passed_time":0.591365459,"remaining_time":0.617970858},
{"learn":[3.952641965],"iteration":489,"passed_time":0.5920524408,"remaining_time":0.6162178466},
{"learn":[3.951486786],"iteration":490,"passed_time":0.5927154186,"remaining_time":0.6144442934},
{"learn":[3.94938344],"iteration":491,"passed_time":0.5936552754,"remaining_time":0.612961138},
{"learn":[3.947297924],"iteration":492,"passed_time":0.5943156792,"remaining_time":0.6111927979},
{"learn":[3.946284886],"iteration":493,"passed_time":0.5949365889,"remaining_time":0.6093884898},
{"learn":[3.943288204],"iteration":494,"passed_time":0.5955986623,"remaining_time":0.6076309585},
{"learn":[3.943076488],"iteration":495,"passed_time":0.5962547751,"remaining_time":0.6058717876},
{"learn":[3.942347078],"iteration":496,"passed_time":0.5969550911,"remaining_time":0.6041617924},
{"learn":[3.940251541],"iteration":497,"passed_time":0.597625746,"remaining_time":0.6024259528},
{"learn":[3.939011019],"iteration":498,"passed_time":0.5983585958,"remaining_time":0.6007568266},
{"learn":[3.938760512],"iteration":499,"passed_time":0.5989774558,"remaining_time":0.5989774558},
{"learn":[3.934522727],"iteration":500,"passed_time":0.5997118308,"remaining_time":0.5973177716},
{"learn":[3.930091193],"iteration":501,"passed_time":0.6004293673,"remaining_time":0.5956450695},
{"learn":[3.927671752],"iteration":502,"passed_time":0.6013253827,"remaining_time":0.5941525154},
{"learn":[3.927280041],"iteration":503,"passed_time":0.6027653049,"remaining_time":0.5931976016},
{"learn":[3.925987561],"iteration":504,"passed_time":0.6035974072,"remaining_time":0.5916449833},
{"learn":[3.921645957],"iteration":505,"passed_time":0.6043320505,"remaining_time":0.5900000651},
{"learn":[3.920333743],"iteration":506,"passed_time":0.605094541,"remaining_time":0.588385816},
{"learn":[3.918659461],"iteration":507,"passed_time":0.6058209625,"remaining_time":0.5867399873},
{"learn":[3.916124385],"iteration":508,"passed_time":0.6065872467,"remaining_time":0.5851362242},
{"learn":[3.913849268],"iteration":509,"passed_time":0.607249499,"remaining_time":0.5834357932},
{"learn":[3.912826119],"iteration":510,"passed_time":0.6079481159,"remaining_time":0.5817742244},
{"learn":[3.910034145],"iteration":511,"passed_time":0.6086520614,"remaining_time":0.580121496},
{"learn":[3.90792379],"iteration":512,"passed_time":0.6093806461,"remaining_time":0.578495857},
{"learn":[3.907823851],"iteration":513,"passed_time":0.6100098662,"remaining_time":0.5767797567},
{"learn":[3.904527401],"iteration":514,"passed_time":0.6107600085,"remaining_time":0.5751817556},
{"learn":[3.903378283],"iteration":515,"passed_time":0.6116296959,"remaining_time":0.5736991721},
{"learn":[3.902170135],"iteration":516,"passed_time":0.6123580188,"remaining_time":0.5720868919},
{"learn":[3.899435429],"iteration":517,"passed_time":0.6131094438,"remaining_time":0.5704995211},
{"learn":[3.897497505],"iteration":518,"passed_time":0.6138066997,"remaining_time":0.5688651687},
{"learn":[3.896426119],"iteration":519,"passed_time":0.6144450915,"remaining_time":0.5671800845},
{"learn":[3.896044669],"iteration":520,"passed_time":0.6152550386,"remaining_time":0.5656567438},
{"learn":[3.892795942],"iteration":521,"passed_time":0.6160594541,"remaining_time":0.564131071},
{"learn":[3.892413888],"iteration":522,"passed_time":0.6171311294,"remaining_time":0.5628519096},
{"learn":[3.891738985],"iteration":523,"passed_time":0.6180064297,"remaining_time":0.5613951537},
{"learn":[3.88822057],"iteration":524,"passed_time":0.6188906792,"remaining_time":0.5599487098},
{"learn":[3.883837053],"iteration":525,"passed_time":0.6196693619,"remaining_time":0.5584092729},
{"learn":[3.881769742],"iteration":526,"passed_time":0.6204567769,"remaining_time":0.5568805607},
{"learn":[3.880356898],"iteration":527,"passed_time":0.6213189395,"remaining_time":0.5554214763},
{"learn":[3.879250273],"iteration":528,"passed_time":0.6219373428,"remaining_time":0.5537476153},
{"learn":[3.877174493],"iteration":529,"passed_time":0.6226526179,"remaining_time":0.5521636422},
{"learn":[3.875854201],"iteration":530,"passed_time":0.6233993971,"remaining_time":0.550610767},
{"learn":[3.873189396],"iteration":531,"passed_time":0.6242354274,"remaining_time":0.5491394361},
{"learn":[3.871583368],"iteration":532,"passed_time":0.6249354545,"remaining_time":0.5475513269},
{"learn":[3.869622679],"iteration":533,"passed_time":0.6256029544,"remaining_time":0.5459381587},
{"learn":[3.866860164],"iteration":534,"passed_time":0.6262997826,"remaining_time":0.5443540167},
{"learn":[3.864498444],"iteration":535,"passed_time":0.6270218267,"remaining_time":0.5427950142},
{"learn":[3.861416322],"iteration":536,"passed_time":0.6277035601,"remaining_time":0.5412043731},
{"learn":[3.860265769],"iteration":537,"passed_time":0.6285109721,"remaining_time":0.5397250355},
{"learn":[3.859328725],"iteration":538,"passed_time":0.62934944,"remaining_time":0.538274753},
{"learn":[3.858521278],"iteration":539,"passed_time":0.6302702026,"remaining_time":0.5368968393},
{"learn":[3.85599111],"iteration":540,"passed_time":0.6309586015,"remaining_time":0.5353234715},
{"learn":[3.852379816],"iteration":541,"passed_time":0.6317649376,"remaining_time":0.5338530284},
{"learn":[3.851327537],"iteration":542,"passed_time":0.6325664856,"remaining_time":0.5323810017},
{"learn":[3.847854898],"iteration":543,"passed_time":0.6333633648,"remaining_time":0.5309075263},
{"learn":[3.847083414],"iteration":544,"passed_time":0.634023701,"remaining_time":0.5293225394},
{"learn":[3.845397429],"iteration":545,"passed_time":0.6349578094,"remaining_time":0.5279685815},
{"learn":[3.841933528],"iteration":546,"passed_time":0.635673028,"remaining_time":0.5264348843},
{"learn":[3.840996474],"iteration":547,"passed_time":0.6363321906,"remaining_time":0.5248579382},
{"learn":[3.838355966],"iteration":548,"passed_time":0.6370229284,"remaining_time":0.5233102745},
{"learn":[3.83342799],"iteration":549,"passed_time":0.6378852995,"remaining_time":0.5219061541},
{"learn":[3.828161535],"iteration":550,"passed_time":0.638698524,"remaining_time":0.5204639515},
{"learn":[3.823502399],"iteration":551,"passed_time":0.6393231981,"remaining_time":0.5188710014},
{"learn":[3.820068862],"iteration":552,"passed_time":0.6404010913,"remaining_time":0.5176478984},
{"learn":[3.817951642],"iteration":553,"passed_time":0.6410773154,"remaining_time":0.5161019543},
{"learn":[3.815785958],"iteration":554,"passed_time":0.6417453649,"remaining_time":0.5145525899},
{"learn":[3.81503012],"iteration":555,"passed_time":0.6425497255,"remaining_time":0.5131152484},
{"learn":[3.813529315],"iteration":556,"passed_time":0.6432405793,"remaining_time":0.5115899042},
{"learn":[3.808881326],"iteration":557,"passed_time":0.6439093473,"remaining_time":0.5100500565},
{"learn":[3.808740434],"iteration":558,"passed_time":0.6448237918,"remaining_time":0.5087071417},
{"learn":[3.80714352],"iteration":559,"passed_time":0.6456599281,"remaining_time":0.5073042292},
{"learn":[3.80573346],"iteration":560,"passed_time":0.6464020562,"remaining_time":0.505829773},
{"learn":[3.803370052],"iteration":561,"passed_time":0.6475995328,"remaining_time":0.5047128032},
{"learn":[3.803215211],"iteration":562,"passed_time":0.6485630425,"remaining_time":0.5034139424},
{"learn":[3.801309667],"iteration":563,"passed_time":0.6493151903,"remaining_time":0.5019528776},
{"learn":[3.800003847],"iteration":564,"passed_time":0.6501296741,"remaining_time":0.5005423155},
{"learn":[3.798026138],"iteration":565,"passed_time":0.651117762,"remaining_time":0.4992669765},
{"learn":[3.794745847],"iteration":566,"passed_time":0.6518943326,"remaining_time":0.4978311217},
{"learn":[3.794312041],"iteration":567,"passed_time":0.6525989946,"remaining_time":0.4963428973},
{"learn":[3.792205926],"iteration":568,"passed_time":0.6533346055,"remaining_time":0.4948808699},
{"learn":[3.788991061],"iteration":569,"passed_time":0.6540427949,"remaining_time":0.4934007049},
{"learn":[3.787391572],"iteration":570,"passed_time":0.6547370032,"remaining_time":0.4919127397},
{"learn":[3.7826445],"iteration":571,"passed_time":0.6555757456,"remaining_time":0.4905356977},
{"learn":[3.781700331],"iteration":572,"passed_time":0.6564536931,"remaining_time":0.4891897504},
{"learn":[3.780045374],"iteration":573,"passed_time":0.6571960021,"remaining_time":0.4877447681},
{"learn":[3.775462644],"iteration":574,"passed_time":0.6579841601,"remaining_time":0.4863361183},
{"learn":[3.773711943],"iteration":575,"passed_time":0.6587533544,"remaining_time":0.4849156637},
{"learn":[3.772415806],"iteration":576,"passed_time":0.6594833309,"remaining_time":0.4834687157},
{"learn":[3.770170875],"iteration":577,"passed_time":0.6601888488,"remaining_time":0.4820063914},
{"learn":[3.765166479],"iteration":578,"passed_time":0.6609671032,"remaining_time":0.480599569},
{"learn":[3.763976102],"iteration":579,"passed_time":0.6617455687,"remaining_time":0.479195067},
{"learn":[3.760761708],"iteration":580,"passed_time":0.6626156387,"remaining_time":0.4778587825},
{"learn":[3.758155662],"iteration":581,"passed_time":0.6633627043,"remaining_time":0.4764357567},
{"learn":[3.756844548],"iteration":582,"passed_time":0.6641286232,"remaining_time":0.4750285349},
{"learn":[3.753098923],"iteration":583,"passed_time":0.6649037245,"remaining_time":0.4736300503},
{"learn":[3.751618946],"iteration":584,"passed_time":0.6656753092,"remaining_time":0.4722312023},
{"learn":[3.751398464],"iteration":585,"passed_time":0.6664428972,"remaining_time":0.4708316714},
{"learn":[3.749920103],"iteration":586,"passed_time":0.6671138822,"remaining_time":0.469366326},
{"learn":[3.748237465],"iteration":587,"passed_time":0.6677939376,"remaining_time":0.4679100379},
{"learn":[3.746021536],"iteration":588,"passed_time":0.6685386381,"remaining_time":0.4665014945},
{"learn":[3.74417648],"iteration":589,"passed_time":0.6694677046,"remaining_time":0.4652233202},
{"learn":[3.738788389],"iteration":590,"passed_time":0.670304468,"remaining_time":0.4638824491},
{"learn":[3.736021611],"iteration":591,"passed_time":0.6710220202,"remaining_time":0.4624611221},
{"learn":[3.734546151],"iteration":592,"passed_time":0.6717634299,"remaining_time":0.4610585429},
{"learn":[3.733527479],"iteration":593,"passed_time":0.6724506543,"remaining_time":0.4596211543},
{"learn":[3.733026392],"iteration":594,"passed_time":0.6731743698,"remaining_time":0.4582111257},
{"learn":[3.730314752],"iteration":595,"passed_time":0.6739084547,"remaining_time":0.456810429},
{"learn":[3.727342596],"iteration":596,"passed_time":0.6746835752,"remaining_time":0.4554396663},
{"learn":[3.725459604],"iteration":597,"passed_time":0.6754431364,"remaining_time":0.4540604362},
{"learn":[3.723158842],"iteration":598,"passed_time":0.6761992532,"remaining_time":0.4526809692},
{"learn":[3.722362756],"iteration":599,"passed_time":0.6769703302,"remaining_time":0.4513135535},
{"learn":[3.721443615],"iteration":600,"passed_time":0.6776848464,"remaining_time":0.4499105719},
{"learn":[3.720743486],"iteration":601,"passed_time":0.6786709588,"remaining_time":0.4486894379},
{"learn":[3.720215334],"iteration":602,"passed_time":0.6795071273,"remaining_time":0.4473703641},
{"learn":[3.719436563],"iteration":603,"passed_time":0.680277288,"remaining_time":0.4460096127},
{"learn":[3.715046574],"iteration":604,"passed_time":0.680884853,"remaining_time":0.4445446561},
{"learn":[3.71443396],"iteration":605,"passed_time":0.6815977726,"remaining_time":0.443151027},
{"learn":[3.712938941],"iteration":606,"passed_time":0.6823257904,"remaining_time":0.4417694162},
{"learn":[3.712814764],"iteration":607,"passed_time":0.6830089662,"remaining_time":0.440361044},
{"learn":[3.71235348],"iteration":608,"passed_time":0.6836778855,"remaining_time":0.4389459002},
{"learn":[3.711223749],"iteration":609,"passed_time":0.6844851796,"remaining_time":0.4376216722},
{"learn":[3.710755648],"iteration":610,"passed_time":0.6852258539,"remaining_time":0.436256722},
{"learn":[3.708668039],"iteration":611,"passed_time":0.6860334562,"remaining_time":0.4349362435},
{"learn":[3.705623591],"iteration":612,"passed_time":0.6867648796,"remaining_time":0.4335693449},
{"learn":[3.704045802],"iteration":613,"passed_time":0.6875030073,"remaining_time":0.4322087309},
{"learn":[3.699915209],"iteration":614,"passed_time":0.6882188899,"remaining_time":0.4308362156},
{"learn":[3.696182221],"iteration":615,"passed_time":0.6889516613,"remaining_time":0.4294763603},
{"learn":[3.694263278],"iteration":616,"passed_time":0.6896423761,"remaining_time":0.4280924312},
{"learn":[3.693810229],"iteration":617,"passed_time":0.6903279662,"remaining_time":0.4267075778},
{"learn":[3.690900932],"iteration":618,"passed_time":0.6910139139,"remaining_time":0.4253252039},
{"learn":[3.688020895],"iteration":619,"passed_time":0.6917026168,"remaining_time":0.4239467651},
{"learn":[3.685491894],"iteration":620,"passed_time":0.6926981976,"remaining_time":0.4227578372},
{"learn":[3.684328128],"iteration":621,"passed_time":0.6936604204,"remaining_time":0.4215492587},
{"learn":[3.680640153],"iteration":622,"passed_time":0.6944751594,"remaining_time":0.4202522233},
{"learn":[3.678932783],"iteration":623,"passed_time":0.6953576986,"remaining_time":0.4189975876},
{"learn":[3.674167041],"iteration":624,"passed_time":0.6960266923,"remaining_time":0.4176160154},
{"learn":[3.672200976],"iteration":625,"passed_time":0.6967789142,"remaining_time":0.4162864439},
{"learn":[3.670606604],"iteration":626,"passed_time":0.6974878458,"remaining_time":0.4149329609},
{"learn":[3.665506042],"iteration":627,"passed_time":0.6981175134,"remaining_time":0.413534578},
{"learn":[3.664214007],"iteration":628,"passed_time":0.6987761525,"remaining_time":0.4121557275},
{"learn":[3.66261643],"iteration":629,"passed_time":0.6995464722,"remaining_time":0.4108447535},
{"learn":[3.662118449],"iteration":630,"passed_time":0.7005604364,"remaining_time":0.4096779731},
{"learn":[3.660871366],"iteration":631,"passed_time":0.7016909822,"remaining_time":0.4085795593},
{"learn":[3.656695243],"iteration":632,"passed_time":0.7024513042,"remaining_time":0.407266396},
{"learn":[3.654497801],"iteration":633,"passed_time":0.7032541322,"remaining_time":0.4059795148},
{"learn":[3.654189134],"iteration":634,"passed_time":0.7040333507,"remaining_time":0.4046805874},
{"learn":[3.653957699],"iteration":635,"passed_time":0.7047284119,"remaining_time":0.4033351288},
{"learn":[3.651920725],"iteration":636,"passed_time":0.7054348503,"remaining_time":0.4019981957},
{"learn":[3.65106705],"iteration":637,"passed_time":0.7062022994,"remaining_time":0.4006978564},
{"learn":[3.650612844],"iteration":638,"passed_time":0.706873976,"remaining_time":0.3993450788},
{"learn":[3.649884732],"iteration":639,"passed_time":0.707586309,"remaining_time":0.3980172988},
{"learn":[3.646276182],"iteration":640,"passed_time":0.7084486996,"remaining_time":0.3967754808},
{"learn":[3.645808194],"iteration":641,"passed_time":0.7091736607,"remaining_time":0.3954582096},
{"learn":[3.645042989],"iteration":642,"passed_time":0.709842111,"remaining_time":0.3941114053},
{"learn":[3.639864499],"iteration":643,"passed_time":0.710630816,"remaining_time":0.392833184},
{"learn":[3.637318478],"iteration":644,"passed_time":0.7117267041,"remaining_time":0.3917255503},
{"learn":[3.636344905],"iteration":645,"passed_time":0.7124889252,"remaining_time":0.3904351076},
{"learn":[3.634754643],"iteration":646,"passed_time":0.7131616926,"remaining_time":0.3890974923},
{"learn":[3.630724975],"iteration":647,"passed_time":0.7138704838,"remaining_time":0.3877814974},
{"learn":[3.629408252],"iteration":648,"passed_time":0.7145591022,"remaining_time":0.3864564636},
{"learn":[3.62790646],"iteration":649,"passed_time":0.7152863616,"remaining_time":0.3851541947},
{"learn":[3.627388973],"iteration":650,"passed_time":0.7159692718,"remaining_time":0.3838299168},
{"learn":[3.625163557],"iteration":651,"passed_time":0.7167494856,"remaining_time":0.3825595414},
{"learn":[3.623701985],"iteration":652,"passed_time":0.7174413396,"remaining_time":0.3812437134},
{"learn":[3.622342639],"iteration":653,"passed_time":0.718153615,"remaining_time":0.3799405976},
{"learn":[3.621130639],"iteration":654,"passed_time":0.7188922489,"remaining_time":0.3786531693},
{"learn":[3.619125665],"iteration":655,"passed_time":0.7195859652,"remaining_time":0.3773438598},
{"learn":[3.618878783],"iteration":656,"passed_time":0.7202858817,"remaining_time":0.3760396612},
{"learn":[3.616207429],"iteration":657,"passed_time":0.7211163735,"remaining_time":0.3748051668},
{"learn":[3.61206486],"iteration":658,"passed_time":0.7219004746,"remaining_time":0.3735478935},
{"learn":[3.611955873],"iteration":659,"passed_time":0.722676963,"remaining_time":0.3722881324},
{"learn":[3.610713743],"iteration":660,"passed_time":0.7236226431,"remaining_time":0.3711166052},
{"learn":[3.610044025],"iteration":661,"passed_time":0.7245088282,"remaining_time":0.3699153836},
{"learn":[3.607342669],"iteration":662,"passed_time":0.7253281247,"remaining_time":0.3686811132},
{"learn":[3.602510618],"iteration":663,"passed_time":0.7260092018,"remaining_time":0.3673781503},
{"learn":[3.600492392],"iteration":664,"passed_time":0.7267950263,"remaining_time":0.3661298253},
{"learn":[3.597171065],"iteration":665,"passed_time":0.7276202248,"remaining_time":0.3649026353},
{"learn":[3.594358798],"iteration":666,"passed_time":0.7288813701,"remaining_time":0.3638942972},
{"learn":[3.593945251],"iteration":667,"passed_time":0.7296832305,"remaining_time":0.3626569349},
{"learn":[3.593607748],"iteration":668,"passed_time":0.7306748906,"remaining_time":0.3615147815},
{"learn":[3.592238714],"iteration":669,"passed_time":0.731694763,"remaining_time":0.3603869728},
{"learn":[3.590144654],"iteration":670,"passed_time":0.7326121223,"remaining_time":0.3592092224},
{"learn":[3.587151536],"iteration":671,"passed_time":0.7333857681,"remaining_time":0.3579621011},
{"learn":[3.586070865],"iteration":672,"passed_time":0.7341407681,"remaining_time":0.3567073271},
{"learn":[3.585102746],"iteration":673,"passed_time":0.7348965041,"remaining_time":0.3554543922},
{"learn":[3.584362847],"iteration":674,"passed_time":0.7355884088,"remaining_time":0.3541721968},
{"learn":[3.581407561],"iteration":675,"passed_time":0.7363277282,"remaining_time":0.3529144733},
{"learn":[3.57919422],"iteration":676,"passed_time":0.7370242617,"remaining_time":0.3516378678},
{"learn":[3.577632204],"iteration":677,"passed_time":0.7381103225,"remaining_time":0.3505479703},
{"learn":[3.573911195],"iteration":678,"passed_time":0.7391269393,"remaining_time":0.3494252541},
{"learn":[3.573408216],"iteration":679,"passed_time":0.7399428821,"remaining_time":0.3482084151},
{"learn":[3.571076482],"iteration":680,"passed_time":0.740654026,"remaining_time":0.3469436627},
{"learn":[3.568177107],"iteration":681,"passed_time":0.7413601274,"remaining_time":0.3456781826},
{"learn":[3.564824621],"iteration":682,"passed_time":0.7421008799,"remaining_time":0.344430423},
{"learn":[3.562475026],"iteration":683,"passed_time":0.7429811857,"remaining_time":0.3432486179},
{"learn":[3.561226889],"iteration":684,"passed_time":0.743735456,"remaining_time":0.3420097352},
{"learn":[3.559383467],"iteration":685,"passed_time":0.7444225974,"remaining_time":0.3407415388},
{"learn":[3.555209766],"iteration":686,"passed_time":0.7451278168,"remaining_time":0.3394832702},
{"learn":[3.55345383],"iteration":687,"passed_time":0.7458264521,"remaining_time":0.3382236236},
{"learn":[3.552300968],"iteration":688,"passed_time":0.7464912276,"remaining_time":0.3369503219},
{"learn":[3.551253986],"iteration":689,"passed_time":0.7472469814,"remaining_time":0.3357196583},
{"learn":[3.549807725],"iteration":690,"passed_time":0.7480272301,"remaining_time":0.3345013229},
{"learn":[3.547992926],"iteration":691,"passed_time":0.7487482367,"remaining_time":0.3332578857},
{"learn":[3.545438607],"iteration":692,"passed_time":0.7495092192,"remaining_time":0.3320336656},
{"learn":[3.543313763],"iteration":693,"passed_time":0.7502509405,"remaining_time":0.3308022879},
{"learn":[3.542962896],"iteration":694,"passed_time":0.7509553599,"remaining_time":0.3295559493},
{"learn":[3.539800465],"iteration":695,"passed_time":0.7517460136,"remaining_time":0.3283488335},
{"learn":[3.53953187],"iteration":696,"passed_time":0.7525260124,"remaining_time":0.3271382809},
{"learn":[3.536332425],"iteration":697,"passed_time":0.7532697012,"remaining_time":0.3259132518},
{"learn":[3.534993327],"iteration":698,"passed_time":0.7540933717,"remaining_time":0.3247240413},
{"learn":[3.531637011],"iteration":699,"passed_time":0.7548729084,"remaining_time":0.3235169608},
{"learn":[3.531040284],"iteration":700,"passed_time":0.7555745107,"remaining_time":0.3222778583},
{"learn":[3.529973872],"iteration":701,"passed_time":0.7567698725,"remaining_time":0.3212498889},
{"learn":[3.527325183],"iteration":702,"passed_time":0.7576241829,"remaining_time":0.3200773575},
{"learn":[3.527200815],"iteration":703,"passed_time":0.7583219285,"remaining_time":0.3188399018},
{"learn":[3.523459911],"iteration":704,"passed_time":0.759043745,"remaining_time":0.3176140493},
{"learn":[3.522729934],"iteration":705,"passed_time":0.7598873438,"remaining_time":0.3164403386},
{"learn":[3.522260582],"iteration":706,"passed_time":0.7606418666,"remaining_time":0.3152306463},
{"learn":[3.518641591],"iteration":707,"passed_time":0.7613323465,"remaining_time":0.3139958265},
{"learn":[3.516856405],"iteration":708,"passed_time":0.7620137215,"remaining_time":0.3127588053},
{"learn":[3.515083413],"iteration":709,"passed_time":0.7627568272,"remaining_time":0.3115485632},
{"learn":[3.514671214],"iteration":710,"passed_time":0.7634675651,"remaining_time":0.3103264787},
{"learn":[3.512617621],"iteration":711,"passed_time":0.7641694199,"remaining_time":0.3091022373},
{"learn":[3.510747971],"iteration":712,"passed_time":0.7648687246,"remaining_time":0.3078784347},
{"learn":[3.508149266],"iteration":713,"passed_time":0.7656343272,"remaining_time":0.3066826577},
{"learn":[3.504557165],"iteration":714,"passed_time":0.7663354834,"remaining_time":0.3054623955},
{"learn":[3.501367208],"iteration":715,"passed_time":0.7670133848,"remaining_time":0.3042343593},
{"learn":[3.497593362],"iteration":716,"passed_time":0.767830715,"remaining_time":0.3030628903},
{"learn":[3.496291169],"iteration":717,"passed_time":0.7686660034,"remaining_time":0.3018994609},
{"learn":[3.49330374],"iteration":718,"passed_time":0.7696219764,"remaining_time":0.3007841104},
{"learn":[3.490044385],"iteration":719,"passed_time":0.7703858682,"remaining_time":0.2995945043},
{"learn":[3.488891789],"iteration":720,"passed_time":0.7712510362,"remaining_time":0.2984452692},
{"learn":[3.486869081],"iteration":721,"passed_time":0.7719211621,"remaining_time":0.2972217217},
{"learn":[3.486303638],"iteration":722,"passed_time":0.7726235382,"remaining_time":0.296012061},
{"learn":[3.486035862],"iteration":723,"passed_time":0.7732981663,"remaining_time":0.2947932236},
{"learn":[3.482668951],"iteration":724,"passed_time":0.774049011,"remaining_time":0.2936047973},
{"learn":[3.47820549],"iteration":725,"passed_time":0.7748579963,"remaining_time":0.2924395193},
{"learn":[3.474392283],"iteration":726,"passed_time":0.7755926258,"remaining_time":0.2912472996},
{"learn":[3.472268163],"iteration":727,"passed_time":0.7763324579,"remaining_time":0.290058281},
{"learn":[3.471209164],"iteration":728,"passed_time":0.7770176097,"remaining_time":0.2888501677},
{"learn":[3.470049971],"iteration":729,"passed_time":0.7776667146,"remaining_time":0.2876301547},
{"learn":[3.469078654],"iteration":730,"passed_time":0.7784144504,"remaining_time":0.2864479988},
{"learn":[3.468643292],"iteration":731,"passed_time":0.7792704861,"remaining_time":0.2853066807},
{"learn":[3.468134848],"iteration":732,"passed_time":0.7800079969,"remaining_time":0.2841229675},
{"learn":[3.467820182],"iteration":733,"passed_time":0.7807210139,"remaining_time":0.2829315936},
{"learn":[3.465776156],"iteration":734,"passed_time":0.7813930744,"remaining_time":0.2817267547},
{"learn":[3.463037608],"iteration":735,"passed_time":0.7820771161,"remaining_time":0.2805276612},
{"learn":[3.45965637],"iteration":736,"passed_time":0.7827752379,"remaining_time":0.2793349899},
{"learn":[3.457275091],"iteration":737,"passed_time":0.783816773,"remaining_time":0.2782655752},
{"learn":[3.455522955],"iteration":738,"passed_time":0.7847142754,"remaining_time":0.2771453665},
{"learn":[3.451270508],"iteration":739,"passed_time":0.7855809233,"remaining_time":0.276014919},
{"learn":[3.450978947],"iteration":740,"passed_time":0.7863842549,"remaining_time":0.2748630526},
{"learn":[3.450608492],"iteration":741,"passed_time":0.7870553442,"remaining_time":0.273666144},
{"learn":[3.448122004],"iteration":742,"passed_time":0.787889551,"remaining_time":0.2725270722},
{"learn":[3.445646714],"iteration":743,"passed_time":0.7885688434,"remaining_time":0.271335516},
{"learn":[3.44411263],"iteration":744,"passed_time":0.7891798551,"remaining_time":0.2701219638},
{"learn":[3.443264164],"iteration":745,"passed_time":0.7898803864,"remaining_time":0.2689405069},
{"learn":[3.439521363],"iteration":746,"passed_time":0.7905625413,"remaining_time":0.2677541137},
{"learn":[3.436809225],"iteration":747,"passed_time":0.791233177,"remaining_time":0.266565188},
{"learn":[3.435509465],"iteration":748,"passed_time":0.7918924832,"remaining_time":0.2653738495},
{"learn":[3.434450277],"iteration":749,"passed_time":0.7928249795,"remaining_time":0.2642749932},
{"learn":[3.431786753],"iteration":750,"passed_time":0.7935467019,"remaining_time":0.2631066961},
{"learn":[3.430150302],"iteration":751,"passed_time":0.7942832578,"remaining_time":0.2619444786},
{"learn":[3.42696281],"iteration":752,"passed_time":0.794985167,"remaining_time":0.2607720269},
{"learn":[3.426870334],"iteration":753,"passed_time":0.7956254235,"remaining_time":0.2595807085},
{"learn":[3.425200309],"iteration":754,"passed_time":0.7963184351,"remaining_time":0.258407969},
{"learn":[3.423383783],"iteration":755,"passed_time":0.7970087365,"remaining_time":0.2572356239},
{"learn":[3.422752979],"iteration":756,"passed_time":0.7977075054,"remaining_time":0.2560672705},
{"learn":[3.420845924],"iteration":757,"passed_time":0.7986387374,"remaining_time":0.2549743726},
{"learn":[3.418917862],"iteration":758,"passed_time":0.7995012589,"remaining_time":0.2538600835},
{"learn":[3.417095735],"iteration":759,"passed_time":0.8003291737,"remaining_time":0.2527355285},
{"learn":[3.414391848],"iteration":760,"passed_time":0.801095854,"remaining_time":0.2515925218},
{"learn":[3.41426711],"iteration":761,"passed_time":0.8019161412,"remaining_time":0.2504672462},
{"learn":[3.411976013],"iteration":762,"passed_time":0.8026541368,"remaining_time":0.2493172089},
{"learn":[3.408614844],"iteration":763,"passed_time":0.8034885788,"remaining_time":0.2481980427},
{"learn":[3.407906721],"iteration":764,"passed_time":0.8042391487,"remaining_time":0.2470538561},
{"learn":[3.407494015],"iteration":765,"passed_time":0.8049459693,"remaining_time":0.2458973327},
{"learn":[3.406287128],"iteration":766,"passed_time":0.8056648565,"remaining_time":0.2447456474},
{"learn":[3.404600442],"iteration":767,"passed_time":0.8064048191,"remaining_time":0.2436014558},
{"learn":[3.404012662],"iteration":768,"passed_time":0.8070935081,"remaining_time":0.2424429134},
{"learn":[3.400398762],"iteration":769,"passed_time":0.8077558656,"remaining_time":0.2412777261},
{"learn":[3.399737714],"iteration":770,"passed_time":0.8084351971,"remaining_time":0.2401188847},
{"learn":[3.399185251],"iteration":771,"passed_time":0.8091245471,"remaining_time":0.2389642445},
{"learn":[3.397245411],"iteration":772,"passed_time":0.809833957,"remaining_time":0.2378166989},
{"learn":[3.396229831],"iteration":773,"passed_time":0.8105987493,"remaining_time":0.2366864565},
{"learn":[3.394002836],"iteration":774,"passed_time":0.811332306,"remaining_time":0.2355480888},
{"learn":[3.389617243],"iteration":775,"passed_time":0.8121042891,"remaining_time":0.2344218567},
{"learn":[3.385426488],"iteration":776,"passed_time":0.8130446284,"remaining_time":0.2333448547},
{"learn":[3.385072258],"iteration":777,"passed_time":0.8138943764,"remaining_time":0.2322423542},
{"learn":[3.383842366],"iteration":778,"passed_time":0.814658844,"remaining_time":0.2311163088},
{"learn":[3.380110746],"iteration":779,"passed_time":0.815550842,"remaining_time":0.2300271606},
{"learn":[3.378595218],"iteration":780,"passed_time":0.816327023,"remaining_time":0.228906041},
{"learn":[3.377371219],"iteration":781,"passed_time":0.8171344553,"remaining_time":0.2277945157},
{"learn":[3.375814782],"iteration":782,"passed_time":0.8178296869,"remaining_time":0.2266526718},
{"learn":[3.374195887],"iteration":783,"passed_time":0.818572562,"remaining_time":0.2255250936},
{"learn":[3.373704309],"iteration":784,"passed_time":0.8194889298,"remaining_time":0.2244460126},
{"learn":[3.372971757],"iteration":785,"passed_time":0.8204535261,"remaining_time":0.2233804766},
{"learn":[3.371565136],"iteration":786,"passed_time":0.8212601086,"remaining_time":0.2222724309},
{"learn":[3.3700309],"iteration":787,"passed_time":0.8219693719,"remaining_time":0.2211389681},
{"learn":[3.368186663],"iteration":788,"passed_time":0.8226801719,"remaining_time":0.2200069915},
{"learn":[3.366710398],"iteration":789,"passed_time":0.8233553743,"remaining_time":0.2188666185},
{"learn":[3.364598042],"iteration":790,"passed_time":0.8240440012,"remaining_time":0.2177309687},
{"learn":[3.36348442],"iteration":791,"passed_time":0.8247869952,"remaining_time":0.216610726},
{"learn":[3.362001759],"iteration":792,"passed_time":0.8255538425,"remaining_time":0.2154976613},
{"learn":[3.361580401],"iteration":793,"passed_time":0.8264501474,"remaining_time":0.2144190559},
{"learn":[3.359543675],"iteration":794,"passed_time":0.8271192409,"remaining_time":0.21328232},
{"learn":[3.35766119],"iteration":795,"passed_time":0.8278104186,"remaining_time":0.2121524188},
{"learn":[3.354592969],"iteration":796,"passed_time":0.8285527624,"remaining_time":0.2110366509},
{"learn":[3.350985986],"iteration":797,"passed_time":0.8295611448,"remaining_time":0.209989162},
{"learn":[3.349589624],"iteration":798,"passed_time":0.8303521546,"remaining_time":0.2088870877},
{"learn":[3.349110856],"iteration":799,"passed_time":0.831062719,"remaining_time":0.2077656798},
{"learn":[3.345315441],"iteration":800,"passed_time":0.8317427721,"remaining_time":0.2066377174},
{"learn":[3.34397474],"iteration":801,"passed_time":0.8324706299,"remaining_time":0.2055226742},
{"learn":[3.343800902],"iteration":802,"passed_time":0.8331904194,"remaining_time":0.204406616},
{"learn":[3.342329465],"iteration":803,"passed_time":0.8338674672,"remaining_time":0.2032811238},
{"learn":[3.34220347],"iteration":804,"passed_time":0.8344985434,"remaining_time":0.2021456099},
{"learn":[3.341279219],"iteration":805,"passed_time":0.8352605949,"remaining_time":0.2010428727},
{"learn":[3.337329521],"iteration":806,"passed_time":0.8359568167,"remaining_time":0.1999252362},
{"learn":[3.336708453],"iteration":807,"passed_time":0.8366706014,"remaining_time":0.1988128162},
{"learn":[3.333252703],"iteration":808,"passed_time":0.8374729262,"remaining_time":0.1977222854},
{"learn":[3.332186769],"iteration":809,"passed_time":0.8382300298,"remaining_time":0.1966218588},
{"learn":[3.330594851],"iteration":810,"passed_time":0.8389120346,"remaining_time":0.1955047775},
{"learn":[3.327867442],"iteration":811,"passed_time":0.8398967741,"remaining_time":0.194458859},
{"learn":[3.327563111],"iteration":812,"passed_time":0.840763123,"remaining_time":0.1933858598},
{"learn":[3.326308994],"iteration":813,"passed_time":0.8414936245,"remaining_time":0.192282327},
{"learn":[3.326249879],"iteration":814,"passed_time":0.8423436182,"remaining_time":0.1912068336},
{"learn":[3.322336238],"iteration":815,"passed_time":0.8431082654,"remaining_time":0.1901126481},
{"learn":[3.320491154],"iteration":816,"passed_time":0.843919372,"remaining_time":0.1890296757},
{"learn":[3.320434271],"iteration":817,"passed_time":0.8446604888,"remaining_time":0.1879317958},
{"learn":[3.319609638],"iteration":818,"passed_time":0.8455221839,"remaining_time":0.186861435},
{"learn":[3.316182682],"iteration":819,"passed_time":0.8462322586,"remaining_time":0.1857583007},
{"learn":[3.313126612],"iteration":820,"passed_time":0.8470923512,"remaining_time":0.1846888318},
{"learn":[3.311222803],"iteration":821,"passed_time":0.8480614178,"remaining_time":0.18364347},
{"learn":[3.309627335],"iteration":822,"passed_time":0.8488035199,"remaining_time":0.1825494812},
{"learn":[3.307974895],"iteration":823,"passed_time":0.8494980768,"remaining_time":0.1814461912},
{"learn":[3.307321505],"iteration":824,"passed_time":0.850223019,"remaining_time":0.1803503374},
{"learn":[3.306759087],"iteration":825,"passed_time":0.850859243,"remaining_time":0.1792366928},
{"learn":[3.30484037],"iteration":826,"passed_time":0.8516049085,"remaining_time":0.1781470969},
{"learn":[3.30201994],"iteration":827,"passed_time":0.8523286694,"remaining_time":0.1770537816},
{"learn":[3.299302297],"iteration":828,"passed_time":0.8530248636,"remaining_time":0.1759556715},
{"learn":[3.298132671],"iteration":829,"passed_time":0.8537114784,"remaining_time":0.1748565679},
{"learn":[3.296976183],"iteration":830,"passed_time":0.8545151432,"remaining_time":0.1737822614},
{"learn":[3.293144745],"iteration":831,"passed_time":0.8554143547,"remaining_time":0.1727278985},
{"learn":[3.290284404],"iteration":832,"passed_time":0.8561473503,"remaining_time":0.1716405852},
{"learn":[3.288285745],"iteration":833,"passed_time":0.8569781952,"remaining_time":0.1705735976},
{"learn":[3.286662667],"iteration":834,"passed_time":0.8580104403,"remaining_time":0.1695469732},
{"learn":[3.285692682],"iteration":835,"passed_time":0.858927504,"remaining_time":0.16849774},
{"learn":[3.284565611],"iteration":836,"passed_time":0.8598344376,"remaining_time":0.1674468499},
{"learn":[3.283897383],"iteration":837,"passed_time":0.8608069467,"remaining_time":0.1664089802},
{"learn":[3.280712855],"iteration":838,"passed_time":0.8616371621,"remaining_time":0.1653439608},
{"learn":[3.280468341],"iteration":839,"passed_time":0.8623735127,"remaining_time":0.1642616215},
{"learn":[3.277814895],"iteration":840,"passed_time":0.8631280543,"remaining_time":0.1631835442},
{"learn":[3.276316385],"iteration":841,"passed_time":0.8639920961,"remaining_time":0.1621267829},
{"learn":[3.27557063],"iteration":842,"passed_time":0.8650525861,"remaining_time":0.1611070653},
{"learn":[3.27499628],"iteration":843,"passed_time":0.8663730181,"remaining_time":0.1601352972},
{"learn":[3.273569958],"iteration":844,"passed_time":0.8675236461,"remaining_time":0.1591315564},
{"learn":[3.269665595],"iteration":845,"passed_time":0.8685664167,"remaining_time":0.1581078347},
{"learn":[3.267984685],"iteration":846,"passed_time":0.8697228151,"remaining_time":0.1571045935},
{"learn":[3.267702508],"iteration":847,"passed_time":0.8706528769,"remaining_time":0.1560604213},
{"learn":[3.266671924],"iteration":848,"passed_time":0.8714610526,"remaining_time":0.1549948398},
{"learn":[3.265359825],"iteration":849,"passed_time":0.8722000558,"remaining_time":0.1539176569},
{"learn":[3.2618983],"iteration":850,"passed_time":0.8729348975,"remaining_time":0.1528405402},
{"learn":[3.260456253],"iteration":851,"passed_time":0.8737513457,"remaining_time":0.1517784028},
{"learn":[3.258389147],"iteration":852,"passed_time":0.8746225384,"remaining_time":0.1507262757},
{"learn":[3.258108469],"iteration":853,"passed_time":0.8754965603,"remaining_time":0.149675056},
{"learn":[3.256424936],"iteration":854,"passed_time":0.8762599405,"remaining_time":0.148605487},
{"learn":[3.254817983],"iteration":855,"passed_time":0.8769867182,"remaining_time":0.147530476},
{"learn":[3.253898449],"iteration":856,"passed_time":0.8776844769,"remaining_time":0.1464514355},
{"learn":[3.253023652],"iteration":857,"passed_time":0.8785362207,"remaining_time":0.1453987685},
{"learn":[3.252845542],"iteration":858,"passed_time":0.8792064841,"remaining_time":0.1443167803},
{"learn":[3.252316026],"iteration":859,"passed_time":0.8798737284,"remaining_time":0.1432352581},
{"learn":[3.24975301],"iteration":860,"passed_time":0.8805230345,"remaining_time":0.1421518023},
{"learn":[3.249151075],"iteration":861,"passed_time":0.8811818248,"remaining_time":0.1410708722},
{"learn":[3.246257135],"iteration":862,"passed_time":0.881864038,"remaining_time":0.1399946387},
{"learn":[3.243826471],"iteration":863,"passed_time":0.8828725958,"remaining_time":0.1389706864},
{"learn":[3.243190653],"iteration":864,"passed_time":0.8837153195,"remaining_time":0.137920888},
{"learn":[3.24008797],"iteration":865,"passed_time":0.8846298005,"remaining_time":0.1368826712},
{"learn":[3.240036811],"iteration":866,"passed_time":0.8854938757,"remaining_time":0.1358370075},
{"learn":[3.238676314],"iteration":867,"passed_time":0.8862478492,"remaining_time":0.1347750185},
{"learn":[3.237848782],"iteration":868,"passed_time":0.886955515,"remaining_time":0.1337067577},
{"learn":[3.236405498],"iteration":869,"passed_time":0.8878310488,"remaining_time":0.1326644096},
{"learn":[3.233378068],"iteration":870,"passed_time":0.8885926588,"remaining_time":0.1316055717},
{"learn":[3.233169169],"iteration":871,"passed_time":0.8894035766,"remaining_time":0.1305546534},
{"learn":[3.232434885],"iteration":872,"passed_time":0.8902925367,"remaining_time":0.1295156382},
{"learn":[3.229978115],"iteration":873,"passed_time":0.8911927822,"remaining_time":0.1284785933},
{"learn":[3.229648848],"iteration":874,"passed_time":0.8920759121,"remaining_time":0.127439416},
{"learn":[3.227208761],"iteration":875,"passed_time":0.893081354,"remaining_time":0.1264179086},
{"learn":[3.226258869],"iteration":876,"passed_time":0.8938932367,"remaining_time":0.1253692909},
{"learn":[3.225331995],"iteration":877,"passed_time":0.8946508604,"remaining_time":0.1243136731},
{"learn":[3.221968268],"iteration":878,"passed_time":0.8953468704,"remaining_time":0.1232502518},
{"learn":[3.221166317],"iteration":879,"passed_time":0.8961069164,"remaining_time":0.1221963977},
{"learn":[3.220047503],"iteration":880,"passed_time":0.8968955047,"remaining_time":0.1211470659},
{"learn":[3.21982781],"iteration":881,"passed_time":0.8975791112,"remaining_time":0.1200842802},
{"learn":[3.216693405],"iteration":882,"passed_time":0.8982729634,"remaining_time":0.1190237109},
{"learn":[3.214798761],"iteration":883,"passed_time":0.8989685089,"remaining_time":0.1179641935},
{"learn":[3.214395085],"iteration":884,"passed_time":0.8996744583,"remaining_time":0.1169068505},
{"learn":[3.213470696],"iteration":885,"passed_time":0.9003582674,"remaining_time":0.115847452},
{"learn":[3.211595017],"iteration":886,"passed_time":0.9010778669,"remaining_time":0.1147934599},
{"learn":[3.210965255],"iteration":887,"passed_time":0.9018994104,"remaining_time":0.1137530788},
{"learn":[3.209413583],"iteration":888,"passed_time":0.9027009341,"remaining_time":0.1127106903},
{"learn":[3.208331683],"iteration":889,"passed_time":0.9034029701,"remaining_time":0.1116565469},
{"learn":[3.207110711],"iteration":890,"passed_time":0.9041797437,"remaining_time":0.1106123368},
{"learn":[3.204519413],"iteration":891,"passed_time":0.9050909657,"remaining_time":0.1095850048},
{"learn":[3.201421296],"iteration":892,"passed_time":0.9057993719,"remaining_time":0.1085336313},
{"learn":[3.200691259],"iteration":893,"passed_time":0.9065147647,"remaining_time":0.1074838535},
{"learn":[3.200485067],"iteration":894,"passed_time":0.9072331437,"remaining_time":0.1064351733},
{"learn":[3.197467568],"iteration":895,"passed_time":0.907934914,"remaining_time":0.1053853025},
{"learn":[3.195838544],"iteration":896,"passed_time":0.9085685143,"remaining_time":0.1043283801},
{"learn":[3.195671746],"iteration":897,"passed_time":0.9091714136,"remaining_time":0.1032689133},
{"learn":[3.194213094],"iteration":898,"passed_time":0.9098386893,"remaining_time":0.1022176948},
{"learn":[3.192884691],"iteration":899,"passed_time":0.910738475,"remaining_time":0.1011931639},
{"learn":[3.188364239],"iteration":900,"passed_time":0.9115546185,"remaining_time":0.1001597195},
{"learn":[3.185219478],"iteration":901,"passed_time":0.9122720498,"remaining_time":0.09911603202},
{"learn":[3.184120387],"iteration":902,"passed_time":0.9129855673,"remaining_time":0.09807264677},
{"learn":[3.183725321],"iteration":903,"passed_time":0.9136690564,"remaining_time":0.09702680245},
{"learn":[3.181264554],"iteration":904,"passed_time":0.9144103716,"remaining_time":0.09598782906},
{"learn":[3.180741589],"iteration":905,"passed_time":0.9154137896,"remaining_time":0.09497670665},
{"learn":[3.179782639],"iteration":906,"passed_time":0.9161400868,"remaining_time":0.09393718641},
{"learn":[3.176377564],"iteration":907,"passed_time":0.9167966064,"remaining_time":0.09289128611},
{"learn":[3.174078182],"iteration":908,"passed_time":0.9175071547,"remaining_time":0.09185165135},
{"learn":[3.171242379],"iteration":909,"passed_time":0.9182166843,"remaining_time":0.09081263911},
{"learn":[3.170421012],"iteration":910,"passed_time":0.9189224771,"remaining_time":0.08977398514},
{"learn":[3.170087224],"iteration":911,"passed_time":0.9197584901,"remaining_time":0.08874862624},
{"learn":[3.167303059],"iteration":912,"passed_time":0.9207519918,"remaining_time":0.08773868925},
{"learn":[3.16705966],"iteration":913,"passed_time":0.9215769512,"remaining_time":0.08671292976},
{"learn":[3.165667683],"iteration":914,"passed_time":0.9223562384,"remaining_time":0.08568336641},
{"learn":[3.164689733],"iteration":915,"passed_time":0.9231148071,"remaining_time":0.08465244956},
{"learn":[3.163311455],"iteration":916,"passed_time":0.9239824641,"remaining_time":0.08363200056},
{"learn":[3.159425016],"iteration":917,"passed_time":0.9247156454,"remaining_time":0.08259987247},
{"learn":[3.159327058],"iteration":918,"passed_time":0.9254913812,"remaining_time":0.08157214567},
{"learn":[3.15819426],"iteration":919,"passed_time":0.9262369265,"remaining_time":0.08054234143},
{"learn":[3.157086603],"iteration":920,"passed_time":0.9269504655,"remaining_time":0.07951040909},
{"learn":[3.153354154],"iteration":921,"passed_time":0.9275792756,"remaining_time":0.07847199946},
{"learn":[3.153261317],"iteration":922,"passed_time":0.9283319266,"remaining_time":0.07744480861},
{"learn":[3.153168454],"iteration":923,"passed_time":0.9290803931,"remaining_time":0.07641786783},
{"learn":[3.152080399],"iteration":924,"passed_time":0.9298889036,"remaining_time":0.07539639759},
{"learn":[3.151635144],"iteration":925,"passed_time":0.9306710288,"remaining_time":0.07437327876},
{"learn":[3.147762655],"iteration":926,"passed_time":0.9313506105,"remaining_time":0.07334260471},
{"learn":[3.147172317],"iteration":927,"passed_time":0.9319862012,"remaining_time":0.07230927423},
{"learn":[3.146254125],"iteration":928,"passed_time":0.9326680951,"remaining_time":0.07128033881},
{"learn":[3.144869828],"iteration":929,"passed_time":0.933485808,"remaining_time":0.07026237265},
{"learn":[3.143466218],"iteration":930,"passed_time":0.9342188074,"remaining_time":0.06923855823},
{"learn":[3.141919643],"iteration":931,"passed_time":0.9350992003,"remaining_time":0.06822612191},
{"learn":[3.141054135],"iteration":932,"passed_time":0.9360100323,"remaining_time":0.06721615452},
{"learn":[3.139390417],"iteration":933,"passed_time":0.9367214181,"remaining_time":0.06619230578},
{"learn":[3.139025283],"iteration":934,"passed_time":0.9375643402,"remaining_time":0.06517826964},
{"learn":[3.137824183],"iteration":935,"passed_time":0.9386354145,"remaining_time":0.06418019928},
{"learn":[3.135620453],"iteration":936,"passed_time":0.9395793225,"remaining_time":0.06317342296},
{"learn":[3.13443178],"iteration":937,"passed_time":0.9402931701,"remaining_time":0.06215157414},
{"learn":[3.132765713],"iteration":938,"passed_time":0.9409965287,"remaining_time":0.06112969995},
{"learn":[3.131434124],"iteration":939,"passed_time":0.9417244364,"remaining_time":0.06011007041},
{"learn":[3.128384262],"iteration":940,"passed_time":0.9424371087,"remaining_time":0.05909010565},
{"learn":[3.128120455],"iteration":941,"passed_time":0.9431133021,"remaining_time":0.05806854726},
{"learn":[3.126314615],"iteration":942,"passed_time":0.943732873,"remaining_time":0.05704429879},
{"learn":[3.125409666],"iteration":943,"passed_time":0.9444032784,"remaining_time":0.05602392329},
{"learn":[3.123072589],"iteration":944,"passed_time":0.9450793206,"remaining_time":0.05500461654},
{"learn":[3.122921099],"iteration":945,"passed_time":0.9457710778,"remaining_time":0.05398693256},
{"learn":[3.122182662],"iteration":946,"passed_time":0.9463934314,"remaining_time":0.05296605265},
{"learn":[3.120040951],"iteration":947,"passed_time":0.9471661353,"remaining_time":0.05195426059},
{"learn":[3.118767799],"iteration":948,"passed_time":0.9481110674,"remaining_time":0.05095222807},
{"learn":[3.118203218],"iteration":949,"passed_time":0.9488260381,"remaining_time":0.04993821253},
{"learn":[3.116343362],"iteration":950,"passed_time":0.9495473083,"remaining_time":0.04892515048},
{"learn":[3.11480829],"iteration":951,"passed_time":0.9503640053,"remaining_time":0.04791751287},
{"learn":[3.112607903],"iteration":952,"passed_time":0.9512787185,"remaining_time":0.04691510994},
{"learn":[3.111661241],"iteration":953,"passed_time":0.9520095432,"remaining_time":0.04590402409},
{"learn":[3.110249676],"iteration":954,"passed_time":0.9530132429,"remaining_time":0.04490638317},
{"learn":[3.107333579],"iteration":955,"passed_time":0.9539168757,"remaining_time":0.04390412398},
{"learn":[3.107149851],"iteration":956,"passed_time":0.9547946117,"remaining_time":0.04290090732},
{"learn":[3.106867336],"iteration":957,"passed_time":0.9556899229,"remaining_time":0.04189872313},
{"learn":[3.10364681],"iteration":958,"passed_time":0.9569111364,"remaining_time":0.04091069509},
{"learn":[3.102703811],"iteration":959,"passed_time":0.9577874796,"remaining_time":0.03990781165},
{"learn":[3.101469264],"iteration":960,"passed_time":0.9586022083,"remaining_time":0.03890269108},
{"learn":[3.09863569],"iteration":961,"passed_time":0.9593502569,"remaining_time":0.03789533239},
{"learn":[3.09645939],"iteration":962,"passed_time":0.9601617826,"remaining_time":0.03689095115},
{"learn":[3.096240186],"iteration":963,"passed_time":0.9612529644,"remaining_time":0.03589741361},
{"learn":[3.094838828],"iteration":964,"passed_time":0.9619301427,"remaining_time":0.03488865802},
{"learn":[3.094176802],"iteration":965,"passed_time":0.9626438536,"remaining_time":0.03388187477},
{"learn":[3.093182279],"iteration":966,"passed_time":0.9634574389,"remaining_time":0.03287910598},
{"learn":[3.090150687],"iteration":967,"passed_time":0.9643910284,"remaining_time":0.03188069515},
{"learn":[3.088612829],"iteration":968,"passed_time":0.965225921,"remaining_time":0.03087926063},
{"learn":[3.087153684],"iteration":969,"passed_time":0.9664076618,"remaining_time":0.02988889676},
{"learn":[3.085866843],"iteration":970,"passed_time":0.9676878453,"remaining_time":0.0289010788},
{"learn":[3.082669094],"iteration":971,"passed_time":0.9686032233,"remaining_time":0.02790215047},
{"learn":[3.081047548],"iteration":972,"passed_time":0.9695638175,"remaining_time":0.02690464858},
{"learn":[3.079684322],"iteration":973,"passed_time":0.9703373175,"remaining_time":0.02590222819},
{"learn":[3.07613431],"iteration":974,"passed_time":0.9712141109,"remaining_time":0.02490292592},
{"learn":[3.074005935],"iteration":975,"passed_time":0.9720873502,"remaining_time":0.0239037873},
{"learn":[3.072988853],"iteration":976,"passed_time":0.9729508113,"remaining_time":0.02290467621},
{"learn":[3.072344268],"iteration":977,"passed_time":0.9738518267,"remaining_time":0.02190668731},
{"learn":[3.070654438],"iteration":978,"passed_time":0.974929875,"remaining_time":0.02091269395},
{"learn":[3.069724506],"iteration":979,"passed_time":0.9757872348,"remaining_time":0.0199140252},
{"learn":[3.067763166],"iteration":980,"passed_time":0.9766936499,"remaining_time":0.01891659465},
{"learn":[3.066737893],"iteration":981,"passed_time":0.9776316444,"remaining_time":0.01791992831},
{"learn":[3.065248174],"iteration":982,"passed_time":0.9784178446,"remaining_time":0.01692075621},
{"learn":[3.063186837],"iteration":983,"passed_time":0.9794192372,"remaining_time":0.01592551605},
{"learn":[3.062880371],"iteration":984,"passed_time":0.9806404623,"remaining_time":0.0149336111},
{"learn":[3.061288645],"iteration":985,"passed_time":0.9816682014,"remaining_time":0.01393849373},
{"learn":[3.059970575],"iteration":986,"passed_time":0.9829636444,"remaining_time":0.01294683625},
{"learn":[3.059576341],"iteration":987,"passed_time":0.9847277011,"remaining_time":0.01196025548},
{"learn":[3.058175919],"iteration":988,"passed_time":0.9860794469,"remaining_time":0.0109675166},
{"learn":[3.056830702],"iteration":989,"passed_time":0.9873887627,"remaining_time":0.009973623865},
{"learn":[3.056336579],"iteration":990,"passed_time":0.9884836072,"remaining_time":0.008977146786},
{"learn":[3.055810414],"iteration":991,"passed_time":0.9897237096,"remaining_time":0.00798164282},
{"learn":[3.055476518],"iteration":992,"passed_time":0.9907646614,"remaining_time":0.006984242326},
{"learn":[3.053331734],"iteration":993,"passed_time":0.9916536387,"remaining_time":0.005985836854},
{"learn":[3.050890374],"iteration":994,"passed_time":0.992624061,"remaining_time":0.004988060608},
{"learn":[3.04972623],"iteration":995,"passed_time":0.9935186713,"remaining_time":0.003990034824},
{"learn":[3.047217327],"iteration":996,"passed_time":0.9946335082,"remaining_time":0.002992879162},
{"learn":[3.047155483],"iteration":997,"passed_time":0.9955570523,"remaining_time":0.001995104313},
{"learn":[3.04430671],"iteration":998,"passed_time":0.9964566599,"remaining_time":0.0009974541141},
{"learn":[3.042664195],"iteration":999,"passed_time":0.9973447956,"remaining_time":0}
]}